{
    "號碼": "071使字第1277號",
    "發照日期": "0711104",
    "原建照": "070建(松山)(五)字第1715號",
    "設計人": "陳重禧(鼎益建築師事務所)",
    "監造人": "陳重禧(鼎益建築師事務所)",
    "承造人": "張秀美(鼎翔營造股份有限公司)",
    "建造類別": "新建",
    "構造種類": "RC造、",
    "使用分區": "住宅區",
    "建物資訊": {
        "棟數": "1",
        "地上層數": "7",
        "地下層數": "1",
        "戶數": "14"
    },
    "建物面積": {
        "騎樓基地面積": "0",
        "其他基地面積": "263.94",
        "建築面積": "147.651",
        "法定空地面積": "0",
        "地上避難面積": "0",
        "地下避難面積": "150.72"
    },
    "簷高": "20",
    "建物高度": "20",
    "工程造價": "5057647",
    "竣工日期": "0711001",
    "開工日期": "0700911",
    "全建築地點": [
        "臺北市松山區松山路312號2樓",
        "臺北市松山區松山路312號3樓",
        "臺北市松山區松山路312號4樓",
        "臺北市松山區松山路312號5樓",
        "臺北市松山區松山路312號6樓",
        "臺北市松山區松山路312號7樓",
        "臺北市松山區松山路312號",
        "臺北市松山區松山路314號2樓",
        "臺北市松山區松山路314號3樓",
        "臺北市松山區松山路314號4樓",
        "臺北市松山區松山路314號5樓",
        "臺北市松山區松山路314號6樓",
        "臺北市松山區松山路314號7樓",
        "臺北市松山區松山路314號"
    ],
    "全地段地號": [
        "臺北市信義區永吉段四小段0014-0000號"
    ],
    "建築概要": [
        "地下001樓,面積:150.72㎡,高度:2.8M,用途:防空避難室",
        "地上001樓,面積:146.03㎡,高度:3M,用途:店舖、集合住宅",
        "地上002樓,面積:147.65㎡,高度:2.8M,用途:集合住宅",
        "地上003樓,面積:147.65㎡,高度:2.8M,用途:集合住宅",
        "地上004樓,面積:147.65㎡,高度:2.8M,用途:集合住宅",
        "地上005樓,面積:147.65㎡,高度:2.8M,用途:集合住宅",
        "地上006樓,面積:147.65㎡,高度:2.8M,用途:集合住宅",
        "地上007樓,面積:147.65㎡,高度:2.8M,用途:集合住宅",
        "突出物001樓,面積:18.46㎡,高度:0M,用途:無"
    ],
    "雜項工作物": [
        "圍牆 長度21.1M"
    ],
    "全停車空間": null,
    "適用法令概要": null,
    "全注意事項": null,
    "變更概要": {}
}