{
    "號碼": "072使字第0761號",
    "發照日期": "0720617",
    "原建照": "071建(松山)(三)字第0542號",
    "設計人": "張大華(張大華建築師事務所)",
    "監造人": "張大華(張大華建築師事務所)",
    "承造人": "康培元(益成工程有限公司)",
    "建造類別": "新建",
    "構造種類": "RC造、",
    "使用分區": "住宅區",
    "建物資訊": {
        "棟數": "1",
        "地上層數": "5",
        "地下層數": "1",
        "戶數": "8"
    },
    "建物面積": {
        "騎樓基地面積": "0",
        "其他基地面積": "255.3",
        "建築面積": "153.175",
        "法定空地面積": "0",
        "地上避難面積": "0",
        "地下避難面積": "96.61"
    },
    "簷高": "15.4",
    "建物高度": "15.4",
    "工程造價": "3037545",
    "竣工日期": "0720527",
    "開工日期": "0710517",
    "全建築地點": [
        "臺北市松山區基隆路一段147巷5弄48號2樓之1",
        "臺北市松山區基隆路一段147巷5弄48號2樓",
        "臺北市松山區基隆路一段147巷5弄48號3樓之1",
        "臺北市松山區基隆路一段147巷5弄48號3樓",
        "臺北市松山區基隆路一段147巷5弄48號4樓之1",
        "臺北市松山區基隆路一段147巷5弄48號4樓",
        "臺北市松山區基隆路一段147巷5弄48號5樓",
        "臺北市松山區基隆路一段147巷5弄48號"
    ],
    "全地段地號": [
        "臺北市信義區雅祥段四小段0474-0001號",
        "臺北市信義區雅祥段四小段0474-0003號",
        "臺北市信義區雅祥段四小段0472-0000號",
        "臺北市信義區雅祥段四小段0474-0000號",
        "臺北市信義區雅祥段四小段0502-0000號"
    ],
    "建築概要": [
        "地下001樓,面積:96.61㎡,高度:2.6M,用途:防空避難室",
        "地上001樓,面積:152.14㎡,高度:3M,用途:集合住宅",
        "地上002樓,面積:152.14㎡,高度:3M,用途:集合住宅",
        "地上003樓,面積:152.14㎡,高度:3M,用途:集合住宅",
        "地上004樓,面積:152.14㎡,高度:3M,用途:集合住宅",
        "地上005樓,面積:152.14㎡,高度:3M,用途:集合住宅",
        "突出物001樓,面積:10.56㎡,高度:0M,用途:無"
    ],
    "雜項工作物": null,
    "全停車空間": null,
    "適用法令概要": null,
    "全注意事項": null,
    "變更概要": {}
}