{
    "號碼": "072建字第1398號",
    "發照日期": "0721003",
    "全設計人": [
        "洪聰明(鴻明建築師事務所)"
    ],
    "建造類別": "新建",
    "構造種類": "RC造",
    "使用分區": "住宅區",
    "建物資訊": {
        "棟數": "1",
        "地上層數": "4",
        "地下層數": "1",
        "戶數": "8"
    },
    "全建築地點": [
        "臺北市士林區福林路255巷7號",
        "臺北市士林區福林路255巷9號"
    ],
    "全地段地號": [
        "臺北市士林區福林段一小段0226-0000號",
        "臺北市士林區福林段一小段0225-0000號"
    ],
    "建物面積": {
        "建築面積": "161.38",
        "其他基地面積": "268.99"
    },
    "建築期限": "自申報開工日起10個月內竣工",
    "工程造價": "2939860",
    "全起造人": [
        "何照義"
    ],
    "全監造人": [
        "洪聰明"
    ],
    "建築概要": [
        "0001棟地下001樓,面積:167.05㎡,高度:2.8M,用途:防空避難室",
        "0001棟地上001樓,面積:161.38㎡,高度:2.9M,用途:集合住宅",
        "0001棟地上002樓,面積:161.38㎡,高度:2.9M,用途:集合住宅",
        "0001棟地上003樓,面積:161.38㎡,高度:2.9M,用途:集合住宅",
        "0001棟地上004樓,面積:159.06㎡,高度:2.78M,用途:集合住宅",
        "0001棟突出物001樓,面積:20.11㎡,高度:2.8M,用途:梯間",
        "0001棟突出物002樓,面積:9.6㎡,高度:1.6M,用途:水箱"
    ],
    "全雜項工作物": null,
    "適用法令概要": null,
    "全注意事項": [
        "拆除執照併案辦理，拆除面積《199.06》平方公尺。"
    ],
    "變更概要": {}
}