{
    "號碼": "074建字第0892號",
    "發照日期": null,
    "全設計人": [
        "陳憲昭(大成建築師事務所)",
        "馬潤源(新基建築師事務所)"
    ],
    "建造類別": "新建",
    "構造種類": "RC造",
    "使用分區": "工業區",
    "建物資訊": {
        "棟數": "2",
        "地上層數": "6",
        "地下層數": "1",
        "戶數": "2"
    },
    "全建築地點": [
        "臺北市萬華區大理街"
    ],
    "全地段地號": [
        "臺北市萬華區華江段三小段0472-0001號"
    ],
    "建物面積": {
        "建築面積": "1420.4",
        "騎樓基地面積": "0",
        "其他基地面積": "2449.6"
    },
    "建築期限": "自申報開工日起15個月內竣工",
    "工程造價": "47612735",
    "全起造人": [
        "世豐塑膠泡綿廠股份有限公司代表人:王世輝"
    ],
    "全監造人": [
        "陳憲昭",
        "馬潤源"
    ],
    "建築概要": [
        "0001棟地下001樓,面積:374.5㎡,高度:3.63M,用途:工廠",
        "0001棟地下001樓,面積:1766.07㎡,高度:3.63M,用途:防空避難室",
        "0001棟地上001樓,面積:1414.46㎡,高度:3.12M,用途:工廠",
        "0001棟地上002樓,面積:1420.4㎡,高度:3.12M,用途:工廠",
        "0001棟地上003樓,面積:1420.4㎡,高度:3.12M,用途:工廠",
        "0001棟地上004樓,面積:1420.4㎡,高度:3.12M,用途:工廠",
        "0001棟地上005樓,面積:1251.25㎡,高度:3.12M,用途:工廠",
        "0001棟地上006樓,面積:1223.73㎡,高度:3.12M,用途:工廠",
        "0001棟突出物001樓,面積:170.54㎡,高度:3M,用途:樓梯間",
        "0001棟突出物002樓,面積:170.54㎡,高度:3M,用途:機械房",
        "0001棟突出物003樓,面積:170.54㎡,高度:3M,用途:水箱"
    ],
    "全雜項工作物": null,
    "適用法令概要": null,
    "全注意事項": [
        "拆除執照併案辦理，拆除面積1418.13平方公尺。",
        "法定空地1028.83平方公尺。"
    ],
    "變更概要": {}
}