{
    "號碼": "078建字第0451號",
    "發照日期": "0780713",
    "全設計人": [
        "何柏村(何柏村建築師事務所)"
    ],
    "建造類別": "新建",
    "構造種類": "RC造",
    "使用分區": "住3",
    "建物資訊": {
        "棟數": "1",
        "地上層數": "7",
        "地下層數": "2",
        "戶數": "12"
    },
    "全建築地點": [
        "臺北市內湖區麗山街"
    ],
    "全地段地號": [
        "臺北市內湖區碧湖段三小段0316-0000號",
        "臺北市內湖區碧湖段三小段0317-0000號",
        "臺北市內湖區碧湖段三小段0327-0001號",
        "臺北市內湖區碧湖段三小段0327-0002號",
        "臺北市內湖區碧湖段三小段0307-0000號",
        "臺北市內湖區碧湖段三小段0325-0001號",
        "臺北市內湖區碧湖段三小段0315-0000號",
        "臺北市內湖區碧湖段三小段0319-0000號"
    ],
    "建物面積": {
        "建築面積": "261.91",
        "其他基地面積": "694.94"
    },
    "建築期限": null,
    "工程造價": "11088551",
    "全起造人": [
        "勵陽建設有限公司負責人：徐獅"
    ],
    "全監造人": [
        "何柏村"
    ],
    "建築概要": [
        "地下001樓,面積:322.18㎡,高度:2.8M,用途:自用儲藏室",
        "地下002樓,面積:509.08㎡,高度:4.4M,用途:防空避難室兼停車場",
        "地上001樓,面積:238.05㎡,高度:4.05M,用途:集合住宅",
        "地上002樓,面積:239.9㎡,高度:2.85M,用途:集合住宅",
        "地上003樓,面積:239.9㎡,高度:2.85M,用途:集合住宅",
        "地上004樓,面積:239.9㎡,高度:2.8M,用途:集合住宅",
        "地上005樓,面積:239.9㎡,高度:2.8M,用途:集合住宅",
        "地上006樓,面積:237.26㎡,高度:5.05M,用途:集合住宅",
        "地上007樓,面積:128.18㎡,高度:2.8M,用途:集合住宅",
        "突出物001樓,面積:15.65㎡,高度:2.7M,用途:樓梯間",
        "突出物002樓,面積:15.32㎡,高度:2.6M,用途:機械房",
        "突出物003樓,面積:13.32㎡,高度:2.5M,用途:水箱"
    ],
    "全雜項工作物": [
        "圍墻 長度38.1M 高度0M 面積0㎡"
    ],
    "適用法令概要": null,
    "全注意事項": [
        "法定空地《433.03》平方公尺。",
        "樓板挑空不得違建若有違建經發現願無條件接受拆除並負擔拆除費用及放棄先訴抗辨權產權移轉及售屋時列入交代申領使照後列管",
        "放樣勘驗前應完成3.2m寬出入通路及公共排水設施並竣工前舖設柏油路面完成"
    ],
    "變更概要": {}
}