{
    "號碼": "077使字第0789號",
    "發照日期": "0771123",
    "原建照": "075建(松北)(中崙)字第1079號",
    "設計人": "陳耀東(陳耀東建築師事務所)",
    "監造人": "陳耀東(陳耀東建築師事務所)",
    "承造人": "曾秋蘭(發泰營造股份有限公司)",
    "建造類別": "新建",
    "構造種類": "RC造",
    "使用分區": "住宅區",
    "建物資訊": {
        "棟數": "2",
        "地上層數": "12",
        "地下層數": "1",
        "戶數": "94"
    },
    "建物面積": {
        "騎樓基地面積": "115.39",
        "其他基地面積": "1319.6",
        "建築面積": "631.72",
        "法定空地面積": "741.74",
        "地上避難面積": "0",
        "地下避難面積": "1028.85"
    },
    "簷高": null,
    "建物高度": "36",
    "工程造價": "35766640",
    "竣工日期": "0770826",
    "開工日期": "0760120",
    "全建築地點": [
        "臺北市松山區光復北路3-1號",
        "臺北市松山區光復北路3號10樓之1",
        "臺北市松山區光復北路3號10樓",
        "臺北市松山區光復北路3號11樓",
        "臺北市松山區光復北路3號12樓之1",
        "臺北市松山區光復北路3號12樓",
        "臺北市松山區光復北路3號2樓之1",
        "臺北市松山區光復北路3號2樓之2",
        "臺北市松山區光復北路3號2樓",
        "臺北市松山區光復北路3號3樓之1",
        "臺北市松山區光復北路3號3樓之2",
        "臺北市松山區光復北路3號3樓",
        "臺北市松山區光復北路3號4樓之1",
        "臺北市松山區光復北路3號4樓之2",
        "臺北市松山區光復北路3號4樓之3",
        "臺北市松山區光復北路3號4樓",
        "臺北市松山區光復北路3號5樓之1",
        "臺北市松山區光復北路3號5樓之2",
        "臺北市松山區光復北路3號5樓之3",
        "臺北市松山區光復北路3號5樓",
        "臺北市松山區光復北路3號6樓之1",
        "臺北市松山區光復北路3號6樓之2",
        "臺北市松山區光復北路3號6樓之3",
        "臺北市松山區光復北路3號6樓之4",
        "臺北市松山區光復北路3號6樓",
        "臺北市松山區光復北路3號7樓之1",
        "臺北市松山區光復北路3號7樓之2",
        "臺北市松山區光復北路3號7樓之3",
        "臺北市松山區光復北路3號7樓",
        "臺北市松山區光復北路3號8樓之1",
        "臺北市松山區光復北路3號8樓之2",
        "臺北市松山區光復北路3號8樓之3",
        "臺北市松山區光復北路3號8樓",
        "臺北市松山區光復北路3號9樓之1",
        "臺北市松山區光復北路3號9樓之2",
        "臺北市松山區光復北路3號9樓",
        "臺北市松山區光復北路3號",
        "臺北市松山區光復北路5號10樓之1",
        "臺北市松山區光復北路5號10樓",
        "臺北市松山區光復北路5號11樓之1",
        "臺北市松山區光復北路5號11樓之2",
        "臺北市松山區光復北路5號11樓",
        "臺北市松山區光復北路5號12樓之1",
        "臺北市松山區光復北路5號12樓之2",
        "臺北市松山區光復北路5號12樓",
        "臺北市松山區光復北路5號2樓之1",
        "臺北市松山區光復北路5號2樓",
        "臺北市松山區光復北路5號3樓之1",
        "臺北市松山區光復北路5號3樓之2",
        "臺北市松山區光復北路5號3樓之3",
        "臺北市松山區光復北路5號3樓之4",
        "臺北市松山區光復北路5號3樓",
        "臺北市松山區光復北路5號4樓之1",
        "臺北市松山區光復北路5號4樓之2",
        "臺北市松山區光復北路5號4樓之3",
        "臺北市松山區光復北路5號4樓之4",
        "臺北市松山區光復北路5號4樓之5",
        "臺北市松山區光復北路5號4樓",
        "臺北市松山區光復北路5號5樓之1",
        "臺北市松山區光復北路5號5樓之2",
        "臺北市松山區光復北路5號5樓之3",
        "臺北市松山區光復北路5號5樓之4",
        "臺北市松山區光復北路5號5樓之5",
        "臺北市松山區光復北路5號5樓之6",
        "臺北市松山區光復北路5號5樓",
        "臺北市松山區光復北路5號6樓之1",
        "臺北市松山區光復北路5號6樓之2",
        "臺北市松山區光復北路5號6樓之3",
        "臺北市松山區光復北路5號6樓之4",
        "臺北市松山區光復北路5號6樓之5",
        "臺北市松山區光復北路5號6樓之6",
        "臺北市松山區光復北路5號6樓",
        "臺北市松山區光復北路5號7樓之1",
        "臺北市松山區光復北路5號7樓之2",
        "臺北市松山區光復北路5號7樓之3",
        "臺北市松山區光復北路5號7樓之4",
        "臺北市松山區光復北路5號7樓之5",
        "臺北市松山區光復北路5號7樓之6",
        "臺北市松山區光復北路5號7樓",
        "臺北市松山區光復北路5號8樓之1",
        "臺北市松山區光復北路5號8樓之2",
        "臺北市松山區光復北路5號8樓之3",
        "臺北市松山區光復北路5號8樓之4",
        "臺北市松山區光復北路5號8樓之5",
        "臺北市松山區光復北路5號8樓之6",
        "臺北市松山區光復北路5號8樓",
        "臺北市松山區光復北路5號9樓之1",
        "臺北市松山區光復北路5號9樓之2",
        "臺北市松山區光復北路5號9樓之3",
        "臺北市松山區光復北路5號9樓之4",
        "臺北市松山區光復北路5號9樓之5",
        "臺北市松山區光復北路5號9樓",
        "臺北市松山區光復北路5號b1樓",
        "臺北市松山區光復北路5號"
    ],
    "全地段地號": [
        "臺北市松山區西松段二小段0690-0000號",
        "臺北市松山區西松段二小段0690-0003號",
        "臺北市松山區西松段二小段0691-0000號",
        "臺北市松山區西松段二小段0692-0000號",
        "臺北市松山區西松段二小段0694-0000號",
        "臺北市松山區西松段二小段0695-0000號",
        "臺北市松山區西松段二小段0695-0003號"
    ],
    "建築概要": [
        "1棟地下001樓,面積:1115.94㎡,高度:3.2M,用途:防空避難室兼停車場；",
        "1棟地下001樓,面積:1115.94㎡,高度:3.2M,用途:一般零售業甲組；",
        "1棟地下001樓,面積:1115.94㎡,高度:3.2M,用途:防空避難室兼停車場；",
        "1棟地下001樓,面積:1115.94㎡,高度:3.2M,用途:一般零售業甲組；",
        "1棟地上001樓,面積:221.24㎡,高度:4.45M,用途:一般零售業甲組；",
        "1棟地上001樓,面積:221.24㎡,高度:4.45M,用途:一般零售業甲組；",
        "1棟地上001樓夾層,面積:37.6㎡,高度:2.8M,用途:自用儲藏室；",
        "1棟地上001樓夾層,面積:37.6㎡,高度:2.8M,用途:自用儲藏室；",
        "1棟地上002樓,面積:221.59㎡,高度:2.85M,用途:集合住宅；",
        "1棟地上002樓,面積:221.59㎡,高度:2.85M,用途:集合住宅；",
        "1棟地上003樓,面積:221.59㎡,高度:2.85M,用途:集合住宅；",
        "1棟地上003樓,面積:221.59㎡,高度:2.85M,用途:集合住宅；",
        "1棟地上004樓,面積:221.59㎡,高度:2.85M,用途:集合住宅；",
        "1棟地上004樓,面積:221.59㎡,高度:2.85M,用途:集合住宅；",
        "1棟地上005樓,面積:221.59㎡,高度:2.85M,用途:集合住宅；",
        "1棟地上005樓,面積:221.59㎡,高度:2.85M,用途:集合住宅；",
        "1棟地上006樓,面積:221.59㎡,高度:2.85M,用途:集合住宅；",
        "1棟地上006樓,面積:221.59㎡,高度:2.85M,用途:集合住宅；",
        "1棟地上007樓,面積:221.59㎡,高度:2.85M,用途:集合住宅；",
        "1棟地上007樓,面積:221.59㎡,高度:2.85M,用途:集合住宅；",
        "1棟地上008樓,面積:221.59㎡,高度:2.85M,用途:集合住宅；",
        "1棟地上008樓,面積:221.59㎡,高度:2.85M,用途:集合住宅；",
        "1棟地上009樓,面積:221.59㎡,高度:2.85M,用途:集合住宅；",
        "1棟地上009樓,面積:221.59㎡,高度:2.85M,用途:集合住宅；",
        "1棟地上010樓,面積:221.59㎡,高度:2.85M,用途:集合住宅；",
        "1棟地上010樓,面積:221.59㎡,高度:2.85M,用途:集合住宅；",
        "1棟地上012樓,面積:221.59㎡,高度:2.73M,用途:集合住宅；",
        "1棟地上012樓,面積:221.59㎡,高度:2.73M,用途:集合住宅；",
        "1棟突出物001樓,面積:27.71㎡,高度:2.8M,用途:梯間；瞭望台；",
        "1棟突出物001樓,面積:27.71㎡,高度:2.8M,用途:梯間；瞭望台；",
        "1棟突出物002樓,面積:27.71㎡,高度:2.5M,用途:機械房；",
        "1棟突出物002樓,面積:27.71㎡,高度:2.5M,用途:機械房；",
        "1棟突出物003樓,面積:27.71㎡,高度:2.5M,用途:水箱；",
        "1棟突出物003樓,面積:27.71㎡,高度:2.5M,用途:水箱；"
    ],
    "雜項工作物": null,
    "全停車空間": [
        "設置類別:平面,車位分類:汽車,檢討類別:法定,室內,地下,輛數:15,面積:212.625㎡"
    ],
    "適用法令概要": null,
    "全注意事項": [
        "1.法定空地面積741.744平方公尺",
        "2.壹層及地下室一般零售業不含餐飲、中西藥、唱片錄音、音響業\n",
        "3.本次僅申辦A棟建物部分使用執照，B棟建物應另行申請辦理"
    ],
    "變更概要": {}
}