{
    "號碼": "077使字第0127號",
    "發照日期": "0770211",
    "原建照": "075建(南港)(南港)字第0017號",
    "設計人": "吳旗清(吳旗清建築師事務所)",
    "監造人": "吳旗清(吳旗清建築師事務所)",
    "承造人": "陳善安(千維營造有限公司)",
    "建造類別": "新建",
    "構造種類": "RC造",
    "使用分區": "住1",
    "建物資訊": {
        "棟數": "1",
        "地上層數": "5",
        "地下層數": "1",
        "戶數": "5"
    },
    "建物面積": {
        "騎樓基地面積": "0",
        "其他基地面積": "246.56",
        "建築面積": "102.77",
        "法定空地面積": "123.28",
        "地上避難面積": "0",
        "地下避難面積": "37.56"
    },
    "簷高": null,
    "建物高度": "14.6",
    "工程造價": "1991010",
    "竣工日期": "0770106",
    "開工日期": "0750324",
    "全建築地點": [
        "臺北市南港區中南街118號",
        "臺北市南港區中南街120號3樓",
        "臺北市南港區中南街120號4樓",
        "臺北市南港區中南街120號5樓",
        "臺北市南港區中南街120號"
    ],
    "全地段地號": [
        "臺北市南港區中南段一小段0245-0000號"
    ],
    "建築概要": [
        "1棟地下001樓,面積:37.56㎡,高度:2.8M,用途:防空避難室；",
        "1棟地下001樓,面積:37.56㎡,高度:2.8M,用途:防空避難室；",
        "1棟地上001樓,面積:102.77㎡,高度:3M,用途:一般零售業百貨；",
        "1棟地上001樓,面積:102.77㎡,高度:3M,用途:一般零售業百貨；",
        "1棟地上002樓,面積:102.77㎡,高度:2.85M,用途:集合住宅；",
        "1棟地上002樓,面積:102.77㎡,高度:2.85M,用途:集合住宅；",
        "1棟地上003樓,面積:102.77㎡,高度:2.85M,用途:集合住宅；",
        "1棟地上003樓,面積:102.77㎡,高度:2.85M,用途:集合住宅；",
        "1棟地上004樓,面積:102.77㎡,高度:2.85M,用途:集合住宅；",
        "1棟地上004樓,面積:102.77㎡,高度:2.85M,用途:集合住宅；",
        "1棟地上005樓,面積:102.77㎡,高度:2.73M,用途:集合住宅；",
        "1棟地上005樓,面積:102.77㎡,高度:2.73M,用途:集合住宅；",
        "1棟突出物001樓,面積:8.45㎡,高度:2.85M,用途:樓梯間；",
        "1棟突出物001樓,面積:8.45㎡,高度:2.85M,用途:樓梯間；",
        "1棟突出物002樓,面積:9㎡,高度:1.25M,用途:水箱；",
        "1棟突出物002樓,面積:9㎡,高度:1.25M,用途:水箱；"
    ],
    "雜項工作物": null,
    "全停車空間": null,
    "適用法令概要": null,
    "全注意事項": [
        "1.西側中南段一小段242地號現有水溝地將來廢止或改道時無條件購買作為",
        "   空地使用本款列入產權移轉交代。",
        "2.法定空地面積123.28平方公尺。"
    ],
    "變更概要": {}
}