{
    "號碼": "077建字第0628號",
    "發照日期": "0770816",
    "全設計人": [
        "李政文(李政文建築師事務所)"
    ],
    "建造類別": "新建",
    "構造種類": "RC造",
    "使用分區": "住宅區",
    "建物資訊": {
        "棟數": "1",
        "地上層數": "5",
        "地下層數": "1",
        "戶數": "9"
    },
    "全建築地點": [
        "臺北市中正區羅斯福路一段9巷2弄"
    ],
    "全地段地號": [
        "臺北市中正區南海段一小段0778-0000號",
        "臺北市中正區南海段一小段0783-0001號",
        "臺北市中正區南海段一小段0780-0000號",
        "臺北市中正區南海段一小段0782-0000號",
        "臺北市中正區南海段一小段0783-0002號",
        "臺北市中正區南海段一小段0783-0000號",
        "臺北市中正區南海段一小段0779-0000號",
        "臺北市中正區南海段一小段0781-0000號"
    ],
    "建物面積": {
        "建築面積": "179.99",
        "騎樓基地面積": "0",
        "其他基地面積": "300"
    },
    "建築期限": "自申報開工日起12個月內竣工",
    "工程造價": "4000283",
    "全起造人": [
        "王忠誠",
        "候翠香",
        "方建華",
        "陳林玉珠",
        "孫秀蘭",
        "孫秀鳳",
        "候政廷",
        "牟敦唐",
        "蔡張寶蓮",
        "張永忠"
    ],
    "全監造人": [
        "李政文"
    ],
    "建築概要": [
        "0001棟地下001樓,面積:213.13㎡,高度:3M,用途:防空避難室",
        "0001棟地上001樓,面積:168.73㎡,高度:4M,用途:日常服務業",
        "0001棟地上002樓,面積:179.99㎡,高度:3M,用途:集合住宅",
        "0001棟地上003樓,面積:179.99㎡,高度:3M,用途:集合住宅",
        "0001棟地上004樓,面積:179.99㎡,高度:3M,用途:集合住宅",
        "0001棟地上005樓,面積:179.99㎡,高度:2.88M,用途:集合住宅",
        "0001棟突出物001樓,面積:22.46㎡,高度:2.65M,用途:樓梯間",
        "0001棟突出物002樓,面積:12.86㎡,高度:2.35M,用途:水箱"
    ],
    "全雜項工作物": null,
    "適用法令概要": null,
    "全注意事項": [
        "法定空地《120.01》平方公尺。",
        "拆除執照併案辦理，拆除面積《337.5》平方公尺。",
        "依台北市綠化實施要點設置。",
        "現有巷道保持現狀不得任意阻塞。"
    ],
    "變更概要": {}
}