{
    "號碼": "075建字第0795號",
    "發照日期": "0750922",
    "全設計人": [
        "邱啟濤(邱啟濤建築師事務所)",
        "賈大燮(賈大&#29205;建築師事務所)"
    ],
    "建造類別": "新建",
    "構造種類": "加強磚造",
    "使用分區": "保護區",
    "建物資訊": {
        "棟數": "5",
        "地上層數": "2",
        "地下層數": "1",
        "戶數": "1"
    },
    "全建築地點": null,
    "全地段地號": [
        "臺北市北投區頂北投段紗帽山小段0374-0000號",
        "臺北市北投區頂北投段紗帽山小段0375-0000號",
        "臺北市北投區頂北投段紗帽山小段0373-0000號",
        "臺北市北投區頂北投段紗帽山小段0378-0000號",
        "臺北市北投區頂北投段紗帽山小段0377-0000號",
        "臺北市北投區頂北投段紗帽山小段0376-0000號",
        "臺北市北投區頂北投段紗帽山小段0703-0000號",
        "臺北市北投區頂北投段紗帽山小段0369-0000號",
        "臺北市北投區頂北投段紗帽山小段0374-0001號"
    ],
    "建物面積": {
        "建築面積": "2919.72",
        "騎樓基地面積": "0",
        "其他基地面積": "99379"
    },
    "建築期限": "自申報開工日起6個月內竣工",
    "工程造價": "19203405",
    "全起造人": [
        "內政部營建署陽明山國家公園管理處處長：劉慶男",
        "　"
    ],
    "全監造人": [
        "邱啟濤",
        "賈大燮"
    ],
    "建築概要": [
        "0001棟地下001樓,面積:1078.55㎡,高度:3M,用途:辦公室",
        "0001棟地上001樓,面積:2919.72㎡,高度:3.76M,用途:管理辦公室、警察宿舍、辦公室、遊客中心(高 3.3；3、3.2、3.3；3.76)",
        "0001棟地上002樓,面積:1476.76㎡,高度:3.57M,用途:管理辦公室、警察宿舍、遊客中心(高 2.55；2.75；3.57)"
    ],
    "全雜項工作物": [
        "擋土牆 長度24M 高度1.5M 面積0㎡"
    ],
    "適用法令概要": null,
    "全注意事項": [
        "法定空地面積《96459.28》平方公尺。",
        "依「台北市建築基地之法定空地實施綠化要點」綠化於申領使照前完成。",
        "防空避難室依建築技術規則第141條規定簽報同意免設。",
        "378、369地號私有土地完成法定徵收程序後方可申領使用執照。"
    ],
    "變更概要": {}
}