{
    "號碼": "100使字第0165號",
    "發照日期": "1000601",
    "原建照": "098建字第0428號",
    "設計人": "陳鴻明(陳鴻明建築師事務所)",
    "監造人": "陳鴻明(陳鴻明建築師事務所)",
    "承造人": "溫兆郎(暉鴻營造有限公司)",
    "建造類別": "新建",
    "構造種類": "RC造",
    "使用分區": "第二種住宅區、山限住宅區",
    "建物資訊": {
        "幢數": "1",
        "棟數": "1",
        "地上層數": "5",
        "地下層數": "0",
        "戶數": "4"
    },
    "建物面積": {
        "騎樓基地面積": "0",
        "其他基地面積": "257.72",
        "建築面積": "88.81",
        "法定空地面積": "167.52",
        "地上避難面積": "0",
        "地下避難面積": "0"
    },
    "簷高": null,
    "建物高度": "17.5",
    "工程造價": "4779859",
    "竣工日期": "1000422",
    "開工日期": "0990301",
    "全建築地點": [
        "臺北市文山區政大二街81號2樓",
        "臺北市文山區政大二街81號3樓",
        "臺北市文山區政大二街81號4樓",
        "臺北市文山區政大二街81號5樓"
    ],
    "全地段地號": [
        "臺北市文山區政大段一小段0105-0001號"
    ],
    "建築概要": [
        "A棟地上001樓,面積:87.57㎡,高度:4.2M,用途:停車空間，水箱，樓電梯間",
        "A棟地上002樓,面積:84.86㎡,高度:3.22M,用途:(H2)集合住宅",
        "A棟地上003樓,面積:84.86㎡,高度:3.22M,用途:(H2)集合住宅",
        "A棟地上004樓,面積:82.86㎡,高度:3.22M,用途:(H2)集合住宅",
        "A棟地上005樓,面積:78.43㎡,高度:3.22M,用途:(H2)集合住宅",
        "A棟突出物001樓,面積:25㎡,高度:2.4M,用途:樓梯間",
        "A棟突出物002樓,面積:25㎡,高度:3.6M,用途:樓梯間，水箱，機械室"
    ],
    "雜項工作物": [
        "圍牆 長度25.39M 高度1.41M",
        "永久性滯洪沉沙池(含流入流出排放管)1座",
        "陰井0.3m*0.3m*0.6m共4座",
        "矩形溝0.3m*0.4m 長度44.71M",
        "臨時性滯洪沉沙池1座",
        "防災土堤及臨時防災措施1式"
    ],
    "全停車空間": [
        "設置類別:平面,車位分類:汽車,檢討類別:法定,室內,地上,輛數:4,面積:13.8㎡",
        "設置類別:平面,車位分類:機車,檢討類別:法定,室內,地上,輛數:4,面積:7.92㎡"
    ],
    "適用法令概要": null,
    "全注意事項": [
        "本案起造人已出具依公寓大廈管理辦法規定提列公寓大廈管理基金之開戶資料影本（於台北富邦銀行公庫部提列公寓大廈管理基金$95,597元），俟大廈管理委員會成立時本基金應予以移交管理。",
        "起造人應於公寓大廈成立管理委員會向本局申請撥付公共基金時，一律將陽台禁止加窗或加設鐵窗等規定納入成為正式規約內容，並向本府完成報備程序，並應於產權移轉及房屋銷售時列入交代。",
        "使用執照核發後二年內，持續加強巡查及不定期檢查，如發現地面層以上(含地面層)之室內停車空間涉有違規室內裝修行為,將依法查處。",
        "地面層設置停車空間，起造人應依原核定用途使用，並將建築物用途詳細告知各承買戶，除於公寓大廈管理規約草約中明確記載外，產權應列入交代，且須轉載於公寓大廈管理規約中。",
        "適用都市設計審議範圍，經本府都市發展局98年09月07日府都設字第09835693500號函完成都市審議程序。",
        "請於卅日內向稅捐稽徵處申報房屋現值及使用情形，如為合法登記之工廠供直接生產使用之自有房屋，請一併申請減半課徵房屋稅；起造人如因買賣、交換、贈與而取得使用執照者，請於核發日起六十日內向稅捐稽徵處申報契稅，以免逾期受罰。",
        "本案由建築師簽證，非屬技術規則第十章應設置無障礙設施及設備之公共建築物。",
        "本案包含1層至5層（梯廳）天花板內部裝修（詳如附表）。",
        "用戶排水設備之管理維護由水道用戶自行負責。",
        "未接入公共污水下水道用戶，俟本市公共污水管線到達後，須依相關規定配合辦理接入。",
        "本案壹樓原核定室內停車空間面積45.9平方公尺，應依核定用途使用，非經辦理用途變更，不得供做其他用途之使用，並應列入產權移交及公寓大廈管理規約。",
        "基地內排水溝應維持暢通，不得堵塞。",
        "（1）使照圖說已註明水土保持設施之安全觀測系統（位置、性質、項目、數量），並說明其監測方式，實測時距及預警系統之方式，應於建物產權移轉時列入交代。",
        "（2）本案沉砂滯洪池應由業主負責，每年至少清疏二次，並視淤積程度適清疏，於建物移轉時列入交代。依設計沉砂池時段於每年6月1日防洪期前定時清理，另不定期於暴雨、颱風過後檢視其內淤砂量，若有超過安全範圍，應隨即予以清理，若因產權移轉亦應由承購人接續上述責任。",
        "（3）請於營運期間設置地層滑動監測系統，以長期監測地層變動情形，如有異常，應即採取必要防止措施。",
        "其他:",
        "1.本建築物設置機械停車設備，該機械停車設備之車位形式、規格(長、寬、高淨尺寸）、操作方式、容車最大尺寸、管理維護規範（含管理維護方式、項目、頻率及經費概估）、使用年限、所有車位操作效率說明（各車進出時間\/總吞吐所需時間）等內容詳設計建築師及停車設備廠商簽認之設備說明書，管理委員會、區分所有權人及停車空",
        "間建築物所有權者，應依設備說明書內容操作管理維護使用。",
        "2.區分所有權人及停車空間建築物所有權者，於辦理產權移轉時，應將上開機械停車設備內容於建築改良物所有權買賣移轉契約書中清楚載明。",
        "3.（95年1月1日以後領得建造執照）建築物陽臺加設窗戶應申請建築執照，未經申請擅自增建即屬違建，應予查報拆除。",
        "4.建築物立面設空調主機處除圖面標註位置外，不得增設空調主機或外掛式設備。",
        "5.起造人應依原核定用途使用，並將建築物用途詳細告知各承買戶，除於公寓大廈管理規約草約中明確記載外，產權應列入交代，且須轉載於公寓大廈管理規約中。"
    ],
    "變更概要": {}
}