{
    "號碼": "100建字第0003號",
    "發照日期": "1000106",
    "全設計人": [
        "黃秀莊(黃秀莊建築師事務所)"
    ],
    "建造類別": "新建",
    "構造種類": "鋼骨RC造(供公眾使用建築物)",
    "使用分區": "第四種商業區(原屬第三種商業區)、第四種商業區(原屬住三)",
    "建物資訊": {
        "幢數": "1",
        "棟數": "1",
        "地上層數": "22",
        "地下層數": "6",
        "戶數": "43"
    },
    "全建築地點": [
        "臺北市中山區南京東路一段"
    ],
    "全地段地號": [
        "臺北市中山區正義段二小段0029-0000號",
        "臺北市中山區正義段二小段0029-0001號",
        "臺北市中山區正義段二小段0030-0000號",
        "臺北市中山區正義段二小段0031-0000號",
        "臺北市中山區正義段二小段0031-0001號",
        "臺北市中山區正義段二小段0032-0000號",
        "臺北市中山區正義段二小段0032-0001號",
        "臺北市中山區正義段二小段0033-0000號",
        "臺北市中山區正義段二小段0033-0001號",
        "臺北市中山區正義段二小段0034-0000號",
        "臺北市中山區正義段二小段0035-0000號",
        "臺北市中山區正義段二小段0035-0001號",
        "臺北市中山區正義段二小段0036-0000號",
        "臺北市中山區正義段二小段0036-0001號",
        "臺北市中山區正義段二小段0037-0000號",
        "臺北市中山區正義段二小段0040-0001號"
    ],
    "建物面積": {
        "建築面積": "790.24",
        "騎樓基地面積": "6.32",
        "其他基地面積": "1357.68"
    },
    "建築期限": "自申報開工日起90個月內竣工",
    "工程造價": "264521655",
    "全起造人": [
        "頂高建設股份有限公司 負責人：陳楊鳳霖"
    ],
    "全監造人": null,
    "建築概要": [
        "地下001樓,面積:1048.62㎡,高度:3.5M,用途:防空避難室兼停車空間",
        "地下002樓,面積:1033.05㎡,高度:3M,用途:停車空間",
        "地下003樓,面積:1008.89㎡,高度:3M,用途:停車空間",
        "地下004樓,面積:963.02㎡,高度:2.9M,用途:停車空間",
        "地下005樓,面積:963.02㎡,高度:2.9M,用途:停車空間",
        "地下006樓,面積:1002.75㎡,高度:2.9M,用途:停車空間",
        "地上000樓,面積:84.17㎡,高度:11.2M,用途:騎樓",
        "地上001樓,面積:637.57㎡,高度:4.2M,用途:一般零售業(甲組)(G3)",
        "地上002樓,面積:432.73㎡,高度:3.5M,用途:一般零售業(甲組)(G3)161.77㎡、防災空間103.65㎡、管委會使用空間79.38㎡、樓梯間87.93㎡",
        "地上003樓,面積:562.66㎡,高度:3.5M,用途:集合住宅(H2)",
        "地上004樓,面積:569.74㎡,高度:3.5M,用途:集合住宅(H2)",
        "地上005樓,面積:569.74㎡,高度:3.5M,用途:集合住宅(H2)",
        "地上006樓,面積:569.74㎡,高度:3.5M,用途:集合住宅(H2)",
        "地上007樓,面積:569.74㎡,高度:3.5M,用途:集合住宅(H2)",
        "地上008樓,面積:569.74㎡,高度:3.5M,用途:集合住宅(H2)",
        "地上009樓,面積:569.74㎡,高度:3.5M,用途:集合住宅(H2)",
        "地上010樓,面積:569.74㎡,高度:3.5M,用途:集合住宅(H2)",
        "地上011樓,面積:569.74㎡,高度:3.5M,用途:集合住宅(H2)424.19㎡、中繼機房34.51㎡、樓梯間111.04㎡",
        "地上012樓,面積:569.74㎡,高度:3.5M,用途:集合住宅(H2)",
        "地上013樓,面積:569.74㎡,高度:3.5M,用途:集合住宅(H2)",
        "地上014樓,面積:569.74㎡,高度:3.5M,用途:集合住宅(H2)",
        "地上015樓,面積:497.96㎡,高度:3.5M,用途:集合住宅(H2)",
        "地上016樓,面積:497.96㎡,高度:3.5M,用途:集合住宅(H2)",
        "地上017樓,面積:497.96㎡,高度:3.5M,用途:集合住宅(H2)",
        "地上018樓,面積:497.96㎡,高度:3.5M,用途:集合住宅(H2)",
        "地上019樓,面積:495.45㎡,高度:3.5M,用途:集合住宅(H2)",
        "地上020樓,面積:499.21㎡,高度:3.5M,用途:集合住宅(H2)",
        "地上021樓,面積:495.45㎡,高度:3.5M,用途:集合住宅(H2)",
        "地上022樓,面積:495.45㎡,高度:3.5M,用途:集合住宅(H2)",
        "突出物001樓,面積:118.53㎡,高度:3.4M,用途:樓梯間",
        "突出物002樓,面積:112.04㎡,高度:3M,用途:機房、水箱",
        "突出物003樓,面積:71.47㎡,高度:2.6M,用途:機房"
    ],
    "全雜項工作物": [
        "圍牆 長度70.77M 高度2M"
    ],
    "適用法令概要": null,
    "全注意事項": [
        "首次掛號日期：《99》年《9》月《21》日（法令適用日期：99年9月21日）。",
        "實設空地《587.49》平方公尺。",
        "依「臺北市建築物及法定空地綠化實施要點」於申領使照前完成綠化。",
        "依「臺北市高層建築物設置集中式共同電視天線設備暫行指導原則」規定辦理。",
        "結構專業技師：《國際隔震結構》技師事務所，技師：《洪維良》結構技師。",
        "地質調查專業技師：復統工程顧問股份有限公司，技師：《侯海樹》土木工程技師。",
        "已領得拆除執照：97拆字第0079號、97拆字第0015號拆除執照。",
        "六樓以上或供公眾使用建築物，建築設備（包括電力、避雷）於申報第一次樓版勘驗（基礎版）時，應檢附有目的事業主管機關核可之文件、專業技師簽證報告及圖說，暨建築師交由專業技師之委託書。",
        "未設置空氣調節設備。",
        "六層以上或供公眾使用建築物，於興建時如規劃設置有中央系統空氣調節工程者，於申領使照前，原設計專業技師或監造專業技師應執行竣工查驗，並檢附原設計專業技師或監造專業技師簽證之竣工圖說。",
        "六層以上或供公眾使用建築物，於興建時如規劃設置有緊急發電機者，原設計專業技師應於設計階段確定後以書面知會消防設備師納入考量，於申領使照前，原設計專業技師應執行竣工查驗，並檢附原設計專業技師及消防設備師簽證之竣工圖說。",
        "昇降機《3》部。",
        "昇降設備應於申領使照前領得升降設備許可證。",
        "放樣勘驗前應完成消防設備審核。",
        "適用都市設計審議範圍，經本府都市發展局《99年10月8日》北市都設字第《09937345100》號函完成都市設計審議程序。",
        "放樣勘驗前應提示污水排水設計圖說送衛工處審查核可文件。",
        "如變更污水排放口位置於申領使照前，應將污水排水設計圖送衛工處申請辦理變更設計。",
        "如位於應設置專用下水道地區或場所，申領使照前應向環保單位申請廢（污）水排放許可證。",
        "放樣勘驗前未開闢計畫道路設計圖說應經新工處審查核可，公共排水溝設計圖說應經水利處審查核可，並依核准圖說打通5.5公尺計畫道路臨基地側4公尺（新建6樓及6樓以上）部分，竣工前完成鋪設柏油路面。",
        "放樣勘驗時應完成車道出入口紅磚斜坡道設計圖說送新工處。",
        "基地坐落臺北航空站（水平面）限建範圍內，經設計建築師檢討限建絕對高度91.92公尺，本案申請建築物絕對高度89.90公尺，尚無影響飛航安全。",
        "本案工程如屬行政院勞工委員會86年1月1日臺86勞檢一字第000001號公告之丁類危險性工作場所，依勞動檢查法第26條規定，施工前應向本府勞工局勞動檢查處申請危險性工作場所審查合格始可使勞工在場作業。",
        "本大樓增設公用停車位21部，位於地下二層，應提供公眾使用。獎勵增加樓地板面積315平方公尺（核計容積率為4.76%），與法定容積樓地板面積6615.83平方公尺（法定容積率為225%）合計後，允建容積樓地板面積為9577.16平方公尺，允建容積率為705.41%。區分所有權人及停車空間建築物所有權者，於產權移轉及房屋銷售時列入交代。",
        "依申請特殊結構審查原則辦理，結構規劃含結構系統（結構平面、主要構架簡圖）及施工方法報告，經99年11月23日(99)省土技字第6874號函認屬可行；詳細結構設計應於申報放樣勘驗前完成結構委託審查。",
        "於本建地開工前，請依「大眾捷運系統兩側禁建限建辦法」第十二條規定通知本局中區工程處辦理會測。",
        "本建案鄰房之建物調查(含已完成之捷運設施)及捷運設施內之監測，請於開工前(或施工中)詳訂納入施工計劃書。",
        "請於基地開工前，通知本局中區工程處，並將施工計劃書送本局中區工程處審查，基地開挖期間之監測紀錄按時提供予本局土木建築設計處及中區工程處。",
        "有關開挖安全監測系統之警戒值、行動值，請依評估報告中之分析結果納入施工計劃書中，以為開工時監測之依據。",
        "該基地建築物完工後申請使用執照前，依上述辦法第18條規定，向本區中區工程處辦理會勘。",
        "本案係容積接受基地，經本府99年12月6日府都規字第09938765500號函核准臺北市士林區海光段1小段12、398、399、401、402、402－1、415、423、424、426、427地號，海光段2小段396地號，中山區榮星段4小段186、421地號、中山區北安段3小段61地號，中山區中山段3小段208地號，中山區長安段1小段1、1－1、1－2地號，中山區福和段1小段889－4地號(以上地號均部分)，以及信義段祥和段2小段503地號，",
        "大同區市府段1小段24、24－1地號等24筆土地移入容積2646.33平方公尺。"
    ],
    "變更概要": {}
}