{
    "號碼": "068使字第0798號",
    "發照日期": "0680525",
    "原建照": "066建(北投)字第0078號",
    "設計人": "(張德霖建築師事務所)",
    "監造人": "(張德霖建築師事務所)",
    "承造人": "宋明珊(潤記營造有限公司)",
    "建造類別": "新建",
    "構造種類": "RC造、",
    "使用分區": "醫院學校特定區",
    "建物資訊": {
        "棟數": "1",
        "地上層數": "2",
        "地下層數": "1",
        "戶數": "1"
    },
    "建物面積": {
        "騎樓基地面積": "0",
        "其他基地面積": "203210.1",
        "建築面積": "38343.522",
        "法定空地面積": "0",
        "地上避難面積": "0",
        "地下避難面積": "471.54"
    },
    "簷高": "10.68",
    "建物高度": "10.68",
    "工程造價": "2841460",
    "竣工日期": "0670811",
    "開工日期": "0660517",
    "全建築地點": [
        "臺北市北投區石牌路二段201號",
        "臺北市北投區石牌路二段201號"
    ],
    "全地段地號": [
        "臺北市北投區唭哩岸段0190-0004號",
        "臺北市北投區唭哩岸段0238-0016號",
        "臺北市北投區唭哩岸段0245-0001號",
        "臺北市北投區唭哩岸段0256-0000號",
        "臺北市北投區唭哩岸段0256-0023號",
        "臺北市北投區唭哩岸段0257-0007號",
        "臺北市北投區唭哩岸段0257-0008號",
        "臺北市北投區唭哩岸段0257-0009號",
        "臺北市北投區唭哩岸段0257-0011號",
        "臺北市北投區唭哩岸段0257-0012號",
        "臺北市北投區唭哩岸段0257-0013號",
        "臺北市北投區唭哩岸段0257-0015號",
        "臺北市北投區唭哩岸段0257-0016號",
        "臺北市北投區唭哩岸段0257-0017號",
        "臺北市北投區唭哩岸段0257-0018號",
        "臺北市北投區唭哩岸段0266-0003號",
        "臺北市北投區唭哩岸段0715-0002號",
        "臺北市北投區唭哩岸段0257-0003號",
        "臺北市北投區唭哩岸段0257-0001號",
        "臺北市北投區唭哩岸段0257-0014號",
        "臺北市北投區唭哩岸段0259-0000號",
        "臺北市北投區唭哩岸段0261-0001號",
        "臺北市北投區唭哩岸段0261-0005號",
        "臺北市北投區唭哩岸段0261-0002號",
        "臺北市北投區唭哩岸段0261-0006號",
        "臺北市北投區唭哩岸段0262-0000號",
        "臺北市北投區唭哩岸段0262-0001號",
        "臺北市北投區唭哩岸段0262-0002號",
        "臺北市北投區唭哩岸段0263-0003號",
        "臺北市北投區唭哩岸段0245-0012號",
        "臺北市北投區唭哩岸段0245-0013號",
        "臺北市北投區唭哩岸段0261-0020號",
        "臺北市北投區唭哩岸段0256-0026號",
        "臺北市北投區唭哩岸段0256-0027號",
        "臺北市北投區唭哩岸段0245-0011號",
        "臺北市北投區唭哩岸段0190-0003號"
    ],
    "建築概要": [
        "地下001樓,面積:471.54㎡,高度:5M,用途:防空避難室",
        "地上001樓,面積:440.44㎡,高度:3.84M,用途:醫院",
        "地上002樓,面積:452.19㎡,高度:3.84M,用途:醫院",
        "突出物001樓,面積:56.56㎡,高度:0M,用途:無"
    ],
    "雜項工作物": null,
    "全停車空間": [
        "設置類別:平面,車位分類:汽車,檢討類別:法定,室外,地上,輛數:5,面積:75㎡"
    ],
    "適用法令概要": null,
    "全注意事項": null,
    "變更概要": {}
}