{
    "號碼": "086使字第0323號",
    "發照日期": "0860904",
    "原建照": "083建字第0138號",
    "設計人": "陶運昌(陶運昌)",
    "監造人": "陶運昌(陶運昌)",
    "承造人": "顧誠(九達營造工程股份有限公司)",
    "建造類別": "新建",
    "構造種類": "RC造",
    "使用分區": "商3",
    "建物資訊": {
        "棟數": "1",
        "地上層數": "9",
        "地下層數": "3",
        "戶數": "10"
    },
    "建物面積": {
        "騎樓基地面積": "39.13",
        "其他基地面積": "527.87",
        "建築面積": "371.02",
        "法定空地面積": "161.49",
        "地上避難面積": "0",
        "地下避難面積": "523.2"
    },
    "簷高": "0",
    "建物高度": "30.25",
    "工程造價": "40996345",
    "竣工日期": "0880903",
    "開工日期": "0840105",
    "全建築地點": [
        "臺北市大同區民生西路286號2樓",
        "臺北市大同區民生西路286號3樓",
        "臺北市大同區民生西路286號4樓",
        "臺北市大同區民生西路286號5樓",
        "臺北市大同區民生西路286號6樓",
        "臺北市大同區民生西路286號7樓",
        "臺北市大同區民生西路286號8樓",
        "臺北市大同區民生西路286號9樓",
        "臺北市大同區民生西路286號b1樓",
        "臺北市大同區民生西路286號"
    ],
    "全地段地號": [
        "臺北市大同區迪化段一小段0037-0000號",
        "臺北市大同區迪化段一小段0038-0000號"
    ],
    "建築概要": [
        "地下001樓,面積:523.2㎡,高度:3.6M,用途:金融分支機構(銀行分行)",
        "地下002樓,面積:523.2㎡,高度:3.1M,用途:停車場",
        "地下003樓,面積:523.2㎡,高度:4.3M,用途:防空避難室兼停車空間",
        "地上001樓,面積:351.31㎡,高度:4.2M,用途:金融分支機構(銀行分行)",
        "地上002樓,面積:350.72㎡,高度:3.2M,用途:金融分支機構(銀行分行)",
        "地上003樓,面積:384.87㎡,高度:3.2M,用途:金融分支機構(銀行分行)",
        "地上004樓,面積:384.87㎡,高度:3.2M,用途:金融分支機構(銀行分行)",
        "地上005樓,面積:384.87㎡,高度:3.2M,用途:金融分支機構(銀行分行)",
        "地上006樓,面積:384.87㎡,高度:3.2M,用途:金融分支機構(銀行分行)",
        "地上007樓,面積:384.87㎡,高度:3.2M,用途:金融分支機構(銀行分行)",
        "地上008樓,面積:368㎡,高度:3.2M,用途:金融分支機構(銀行分支)",
        "地上009樓,面積:149.7㎡,高度:3.2M,用途:金融分支機構(銀行分行)",
        "地上009樓夾層,面積:13.91㎡,高度:3.2M,用途:樓梯間",
        "突出物001樓,面積:22.35㎡,高度:2.8M,用途:樓梯間",
        "突出物002樓,面積:22.35㎡,高度:2.8M,用途:機械室、機房",
        "突出物003樓,面積:22.35㎡,高度:2.5M,用途:水箱、水塔"
    ],
    "雜項工作物": [
        "圍墻長度12.75M高度2.00M"
    ],
    "全停車空間": [
        "設置類別:平面,車位分類:汽車,檢討類別:法定,室內,地下,輛數:11,面積:158.81㎡",
        "設置類別:平面,車位分類:汽車,檢討類別:自設,室內,地下,輛數:5,面積:68.81㎡"
    ],
    "適用法令概要": null,
    "全注意事項": [
        "昇降設備需取得使用許可證後方得使用",
        "退縮騎樓地已計入空地比不得增建騎樓",
        "本案停車位與鄰地39,40地號(83建字第175號建照)合併留設(合計法定14輛,實設20輛)"
    ],
    "變更概要": {}
}