{
    "號碼": "089使字第0240號",
    "發照日期": "0890721",
    "原建照": "086建字第0396號",
    "設計人": "唐洪之(唐洪之)",
    "監造人": "唐洪之(唐洪之)",
    "承造人": "章啟光(太平洋建設股份有限公司)",
    "建造類別": "新建",
    "構造種類": "RC造",
    "使用分區": "住3",
    "建物資訊": {
        "棟數": "4",
        "地上層數": "10",
        "地下層數": "1",
        "戶數": "144"
    },
    "建物面積": {
        "騎樓基地面積": "0",
        "其他基地面積": "3377.76",
        "建築面積": "1019.05",
        "法定空地面積": "2323.54",
        "地上避難面積": "0",
        "地下避難面積": "2781.87"
    },
    "簷高": null,
    "建物高度": "30.6",
    "工程造價": "106293010",
    "竣工日期": "0890413",
    "開工日期": "0870522",
    "全建築地點": [
        "臺北市文山區福興路95巷47號2樓之1",
        "臺北市文山區福興路95巷47號2樓",
        "臺北市文山區福興路95巷47號3樓之1",
        "臺北市文山區福興路95巷47號3樓",
        "臺北市文山區福興路95巷47號4樓之1",
        "臺北市文山區福興路95巷47號4樓",
        "臺北市文山區福興路95巷47號5樓之1",
        "臺北市文山區福興路95巷47號5樓",
        "臺北市文山區福興路95巷47號6樓之1",
        "臺北市文山區福興路95巷47號6樓",
        "臺北市文山區福興路95巷47號7樓之1",
        "臺北市文山區福興路95巷47號7樓",
        "臺北市文山區福興路95巷47號8樓之1",
        "臺北市文山區福興路95巷47號8樓",
        "臺北市文山區福興路95巷47號9樓之1",
        "臺北市文山區福興路95巷47號9樓",
        "臺北市文山區福興路95巷47號",
        "臺北市文山區福興路95巷49號2樓",
        "臺北市文山區福興路95巷49號3樓",
        "臺北市文山區福興路95巷49號4樓",
        "臺北市文山區福興路95巷49號5樓",
        "臺北市文山區福興路95巷49號6樓",
        "臺北市文山區福興路95巷49號7樓",
        "臺北市文山區福興路95巷49號8樓",
        "臺北市文山區福興路95巷49號9樓",
        "臺北市文山區福興路95巷49號",
        "臺北市文山區福興路95巷51號2樓",
        "臺北市文山區福興路95巷51號3樓",
        "臺北市文山區福興路95巷51號4樓",
        "臺北市文山區福興路95巷51號5樓",
        "臺北市文山區福興路95巷51號6樓",
        "臺北市文山區福興路95巷51號7樓",
        "臺北市文山區福興路95巷51號8樓",
        "臺北市文山區福興路95巷51號9樓",
        "臺北市文山區福興路95巷51號",
        "臺北市文山區福興路95巷53號2樓之1",
        "臺北市文山區福興路95巷53號2樓",
        "臺北市文山區福興路95巷53號3樓之1",
        "臺北市文山區福興路95巷53號3樓",
        "臺北市文山區福興路95巷53號4樓之1",
        "臺北市文山區福興路95巷53號4樓",
        "臺北市文山區福興路95巷53號5樓之1",
        "臺北市文山區福興路95巷53號5樓",
        "臺北市文山區福興路95巷53號6樓之1",
        "臺北市文山區福興路95巷53號6樓",
        "臺北市文山區福興路95巷53號7樓之1",
        "臺北市文山區福興路95巷53號7樓",
        "臺北市文山區福興路95巷53號8樓之1",
        "臺北市文山區福興路95巷53號8樓",
        "臺北市文山區福興路95巷53號9樓之1",
        "臺北市文山區福興路95巷53號9樓",
        "臺北市文山區福興路95巷53號",
        "臺北市文山區福興路95巷55號2樓",
        "臺北市文山區福興路95巷55號3樓",
        "臺北市文山區福興路95巷55號4樓",
        "臺北市文山區福興路95巷55號5樓",
        "臺北市文山區福興路95巷55號6樓",
        "臺北市文山區福興路95巷55號7樓",
        "臺北市文山區福興路95巷55號8樓",
        "臺北市文山區福興路95巷55號9樓",
        "臺北市文山區福興路95巷55號",
        "臺北市文山區福興路95巷57號2樓",
        "臺北市文山區福興路95巷57號3樓",
        "臺北市文山區福興路95巷57號4樓",
        "臺北市文山區福興路95巷57號5樓",
        "臺北市文山區福興路95巷57號6樓",
        "臺北市文山區福興路95巷57號7樓",
        "臺北市文山區福興路95巷57號8樓",
        "臺北市文山區福興路95巷57號9樓",
        "臺北市文山區福興路95巷57號",
        "臺北市文山區福興路95巷59號10樓",
        "臺北市文山區福興路95巷59號2樓之1",
        "臺北市文山區福興路95巷59號2樓",
        "臺北市文山區福興路95巷59號3樓之1",
        "臺北市文山區福興路95巷59號3樓",
        "臺北市文山區福興路95巷59號4樓之1",
        "臺北市文山區福興路95巷59號4樓",
        "臺北市文山區福興路95巷59號5樓之1",
        "臺北市文山區福興路95巷59號5樓",
        "臺北市文山區福興路95巷59號6樓之1",
        "臺北市文山區福興路95巷59號6樓",
        "臺北市文山區福興路95巷59號7樓之1",
        "臺北市文山區福興路95巷59號7樓",
        "臺北市文山區福興路95巷59號8樓之1",
        "臺北市文山區福興路95巷59號8樓",
        "臺北市文山區福興路95巷59號9樓之1",
        "臺北市文山區福興路95巷59號9樓",
        "臺北市文山區福興路95巷59號",
        "臺北市文山區福興路95巷61號2樓",
        "臺北市文山區福興路95巷61號3樓",
        "臺北市文山區福興路95巷61號4樓",
        "臺北市文山區福興路95巷61號5樓",
        "臺北市文山區福興路95巷61號6樓",
        "臺北市文山區福興路95巷61號7樓",
        "臺北市文山區福興路95巷61號8樓",
        "臺北市文山區福興路95巷61號9樓",
        "臺北市文山區福興路95巷61號",
        "臺北市文山區福興路95巷63號10樓",
        "臺北市文山區福興路95巷63號2樓",
        "臺北市文山區福興路95巷63號3樓",
        "臺北市文山區福興路95巷63號4樓",
        "臺北市文山區福興路95巷63號5樓",
        "臺北市文山區福興路95巷63號6樓",
        "臺北市文山區福興路95巷63號7樓",
        "臺北市文山區福興路95巷63號8樓",
        "臺北市文山區福興路95巷63號9樓",
        "臺北市文山區福興路95巷63號",
        "臺北市文山區福興路95巷65號10樓",
        "臺北市文山區福興路95巷65號2樓之1",
        "臺北市文山區福興路95巷65號2樓",
        "臺北市文山區福興路95巷65號3樓之1",
        "臺北市文山區福興路95巷65號3樓",
        "臺北市文山區福興路95巷65號4樓之1",
        "臺北市文山區福興路95巷65號4樓",
        "臺北市文山區福興路95巷65號5樓之1",
        "臺北市文山區福興路95巷65號5樓",
        "臺北市文山區福興路95巷65號6樓之1",
        "臺北市文山區福興路95巷65號6樓",
        "臺北市文山區福興路95巷65號7樓之1",
        "臺北市文山區福興路95巷65號7樓",
        "臺北市文山區福興路95巷65號8樓之1",
        "臺北市文山區福興路95巷65號8樓",
        "臺北市文山區福興路95巷65號9樓之1",
        "臺北市文山區福興路95巷65號9樓",
        "臺北市文山區福興路95巷65號b1樓",
        "臺北市文山區福興路95巷65號",
        "臺北市文山區福興路95巷67號10樓",
        "臺北市文山區福興路95巷67號2樓之1",
        "臺北市文山區福興路95巷67號2樓",
        "臺北市文山區福興路95巷67號3樓之1",
        "臺北市文山區福興路95巷67號3樓",
        "臺北市文山區福興路95巷67號4樓之1",
        "臺北市文山區福興路95巷67號4樓",
        "臺北市文山區福興路95巷67號5樓之1",
        "臺北市文山區福興路95巷67號5樓",
        "臺北市文山區福興路95巷67號6樓之1",
        "臺北市文山區福興路95巷67號6樓",
        "臺北市文山區福興路95巷67號7樓之1",
        "臺北市文山區福興路95巷67號7樓",
        "臺北市文山區福興路95巷67號8樓之1",
        "臺北市文山區福興路95巷67號8樓",
        "臺北市文山區福興路95巷67號9樓之1",
        "臺北市文山區福興路95巷67號9樓",
        "臺北市文山區福興路95巷67號"
    ],
    "全地段地號": [
        "臺北市文山區興隆段一小段0376-0000號",
        "臺北市文山區興隆段一小段0377-0000號",
        "臺北市文山區興隆段一小段0378-0002號",
        "臺北市文山區興隆段一小段0379-0000號",
        "臺北市文山區興隆段一小段0380-0000號",
        "臺北市文山區興隆段一小段0381-0000號",
        "臺北市文山區興隆段一小段0382-0002號",
        "臺北市文山區興隆段一小段0384-0000號",
        "臺北市文山區興隆段一小段0385-0000號"
    ],
    "建築概要": [
        "H棟地上001樓,面積:253.17㎡,高度:3.6M,用途:集合住宅",
        "H棟地上002樓,面積:253.17㎡,高度:3M,用途:集合住宅",
        "H棟地上003樓,面積:253.17㎡,高度:3M,用途:集合住宅",
        "H棟地上004樓,面積:253.17㎡,高度:3M,用途:集合住宅",
        "H棟地上005樓,面積:253.17㎡,高度:3M,用途:集合住宅",
        "H棟地上006樓,面積:253.17㎡,高度:3M,用途:集合住宅",
        "H棟地上007樓,面積:253.17㎡,高度:3M,用途:集合住宅",
        "H棟地上008樓,面積:253.17㎡,高度:3M,用途:集合住宅",
        "H棟地上009樓,面積:253.17㎡,高度:3M,用途:集合住宅",
        "H棟突出物001樓,面積:29.86㎡,高度:3M,用途:梯間",
        "H棟突出物002樓,面積:29.86㎡,高度:3M,用途:機房",
        "H棟突出物003樓,面積:5.31㎡,高度:3M,用途:水箱",
        "J棟地上001樓,面積:253.17㎡,高度:3.6M,用途:集合住宅",
        "J棟地上002樓,面積:253.17㎡,高度:3M,用途:集合住宅",
        "J棟地上003樓,面積:253.17㎡,高度:3M,用途:集合住宅",
        "J棟地上004樓,面積:253.17㎡,高度:3M,用途:集合住宅",
        "J棟地上005樓,面積:253.17㎡,高度:3M,用途:集合住宅",
        "J棟地上006樓,面積:253.17㎡,高度:3M,用途:集合住宅",
        "J棟地上007樓,面積:253.17㎡,高度:3M,用途:集合住宅",
        "J棟地上008樓,面積:253.17㎡,高度:3M,用途:集合住宅",
        "J棟地上009樓,面積:253.17㎡,高度:3M,用途:集合住宅",
        "J棟突出物001樓,面積:29.86㎡,高度:3M,用途:梯間",
        "J棟突出物002樓,面積:29.86㎡,高度:3M,用途:機房",
        "J棟突出物003樓,面積:5.31㎡,高度:3M,用途:水箱",
        "K棟地上001樓,面積:252.4㎡,高度:3.6M,用途:集合住宅",
        "K棟地上002樓,面積:252.4㎡,高度:3M,用途:集合住宅",
        "K棟地上003樓,面積:252.4㎡,高度:3M,用途:集合住宅",
        "K棟地上004樓,面積:252.4㎡,高度:3M,用途:集合住宅",
        "K棟地上005樓,面積:252.4㎡,高度:3M,用途:集合住宅",
        "K棟地上006樓,面積:252.4㎡,高度:3M,用途:集合住宅",
        "K棟地上007樓,面積:252.4㎡,高度:3M,用途:集合住宅",
        "K棟地上008樓,面積:252.4㎡,高度:3M,用途:集合住宅",
        "K棟地上009樓,面積:252.4㎡,高度:3M,用途:集合住宅",
        "K棟地上010樓,面積:156.16㎡,高度:3M,用途:集合住宅",
        "K棟突出物001樓,面積:29.86㎡,高度:3M,用途:梯間",
        "K棟突出物002樓,面積:29.86㎡,高度:3M,用途:機房",
        "K棟突出物003樓,面積:5.31㎡,高度:3M,用途:水箱",
        "L棟地上001樓,面積:7.91㎡,高度:3.6M,用途:警衛室",
        "L棟地上001樓,面積:247.96㎡,高度:3.6M,用途:集合住宅",
        "L棟地上002樓,面積:252.4㎡,高度:3M,用途:集合住宅",
        "L棟地上003樓,面積:252.4㎡,高度:3M,用途:集合住宅",
        "L棟地上004樓,面積:252.4㎡,高度:3M,用途:集合住宅",
        "L棟地上005樓,面積:252.4㎡,高度:3M,用途:集合住宅",
        "L棟地上006樓,面積:252.4㎡,高度:3M,用途:集合住宅",
        "L棟地上007樓,面積:252.4㎡,高度:3M,用途:集合住宅",
        "L棟地上008樓,面積:252.4㎡,高度:3M,用途:集合住宅",
        "L棟地上009樓,面積:252.4㎡,高度:3M,用途:集合住宅",
        "L棟地上010樓,面積:156.16㎡,高度:3M,用途:集合住宅",
        "L棟突出物001樓,面積:29.86㎡,高度:3M,用途:梯間",
        "L棟突出物002樓,面積:29.86㎡,高度:3M,用途:機房",
        "L棟突出物003樓,面積:5.31㎡,高度:3M,用途:水箱",
        "地下001樓,面積:47.02㎡,高度:4.45M,用途:一般事務所",
        "地下001樓,面積:2781.87㎡,高度:4.45M,用途:防空避難室兼停車空間"
    ],
    "雜項工作物": null,
    "全停車空間": [
        "設置類別:平面,車位分類:汽車,檢討類別:法定,室內,地下,輛數:64,面積:904.31㎡",
        "設置類別:平面,車位分類:汽車,檢討類別:自設,室內,地下,輛數:8,面積:107.63㎡"
    ],
    "適用法令概要": null,
    "全注意事項": [
        "依台北市土地使用分區規則第11章綜合設計放寬規定辦理",
        "開放空間面積1691.06平方公尺，獎勵增加樓地板面積1521.95平方公尺",
        "切結H、J棟門廊部份不登記為私人產權，且於住戶公約上載明",
        "用戶排水設備之管理維護由水道用戶自行負責",
        "未接入公共污水下水道用戶，俟本市公共污水管線到達後，須依相關規定配合辦理接入",
        "建築物樓層中任意加設夾層者均係屬違建，不因使用材質而視為室內裝修，除應無條件接受拆除並負擔拆除費用",
        "本建築未經本市建造執照特殊結構委託審查單位鑑定，擅自違建夾層一經檢舉查報即以新違建認定，即報即拆",
        "請於卅日內向稅捐稽徵處申報房屋現值及使用情形，起造人如因買賣、交換、贈與而取得使用執照者，請於核發日起六十日內向稅捐稽徵處申報契稅，以免逾期受罰",
        "本案基地西北側計畫道路，人行步道配合既成道路暫時調整，將來該計畫道路開闢時，太平洋建設股份有限公司切結無條件修正至原設計標高，產權移轉時列入交代"
    ],
    "變更概要": {}
}