{
    "號碼": "089建字第0389號",
    "發照日期": "0891212",
    "全設計人": [
        "杜金木(杜金木)"
    ],
    "建造類別": "新建",
    "構造種類": "RC造(非供公眾使用建築物)",
    "使用分區": "住2",
    "建物資訊": {
        "棟數": "1",
        "地上層數": "4",
        "地下層數": "2",
        "戶數": "5"
    },
    "全建築地點": null,
    "全地段地號": [
        "臺北市北投區桃源段四小段0106-0000號"
    ],
    "建物面積": {
        "建築面積": "189.34",
        "其他基地面積": "551.35"
    },
    "建築期限": "自申報開工日起16個月內竣工",
    "工程造價": "9791951",
    "全起造人": [
        "林萬吉",
        "林哲宏(法定代理人:林松木)",
        "林哲榮",
        "林哲彥",
        "林育全(法定代理人:林萬吉)"
    ],
    "全監造人": [
        "杜金木"
    ],
    "建築概要": [
        "*棟地上001樓,面積:189.34㎡,高度:4.2M,用途:集合住宅",
        "*棟地上002樓,面積:162.57㎡,高度:4.2M,用途:集合住宅",
        "*棟突出物001樓,面積:23.63㎡,高度:4.2M,用途:梯間.水箱",
        "*棟突出物002樓,面積:16.71㎡,高度:4.2M,用途:梯間.機械室",
        "地下001樓,面積:348.19㎡,高度:4.2M,用途:停車空間",
        "地下002樓,面積:348.19㎡,高度:4.2M,用途:停車空間",
        "地上003樓,面積:181.9㎡,高度:4.2M,用途:集合住宅",
        "地上004樓,面積:145.32㎡,高度:4.2M,用途:集合住宅",
        "突出物003樓,面積:11㎡,高度:4.2M,用途:水箱"
    ],
    "全雜項工作物": [
        "1.圍牆:長度128.92米,高度2.0米"
    ],
    "適用法令概要": null,
    "全注意事項": [
        "法定空地面積 362.01mm .",
        "依「台北市建築物及法定空地綠化實施要點」於申領使照前完成綠化 .",
        "放樣勘驗前應提示污水、 排水設計圖說已送衛工處審查核可文件 .",
        "如變更污水排放口位置於申請使用執照前, 應將污水排水設計圖說先送衛工處申請辦理變更設計 .",
        "如位於應設置專用下水道地區或場所, 應向環保單位申請廢(污水)排放許可證 .",
        "基地內現有巷應維持原狀,不得擅自廢止改道 .",
        "第2層挑空部份切結不得違建,挑空面積26.77平方公尺，若有違建無條件拆除，並須負擔拆除費用，並於產權移轉及房屋銷售時列入交代，使用執照核發後巡查列管",
        "放樣勘驗前應完成消防設備審核 .",
        "捷運設施旁地下室放樣勘驗前應副知捷運局 .",
        "首次掛號日期89年05月29日 .",
        "應依養工處核准圖說,竣工前完成公共排水溝.放樣勘驗公共排水溝等設計圖說",
        "前應經養工處審查核可.",
        "經本府畸零地調處委員會第8806(190)次全體委員大會決議准申請地單獨建築.",
        "建築物樓層內任意加設夾層係屬違建,不因使用材質而視為室內裝修,除應無條",
        "件接受拆除,並須負擔拆除費用.",
        "併案認定建築線(自中央北路之巷口依現有巷道現況中心向兩邊各退縮兩公尺",
        "認定建築線至105與106地號土地臨接認定之建築線足四點八公尺為止)."
    ],
    "變更概要": {}
}