{
    "號碼": "087使字第0488號",
    "發照日期": "0871211",
    "原建照": "085建字第0346號",
    "設計人": "(廖國誠)",
    "監造人": "廖國誠(廖國誠)",
    "承造人": "許太忠(助群營造股份有限公司)",
    "建造類別": "新建",
    "構造種類": "RC造",
    "使用分區": "住3、住3－2",
    "建物資訊": {
        "棟數": "3",
        "地上層數": "13",
        "地下層數": "2",
        "戶數": "196"
    },
    "建物面積": {
        "騎樓基地面積": "0",
        "其他基地面積": "1890",
        "建築面積": "790.94",
        "法定空地面積": "1088.29",
        "地上避難面積": "0",
        "地下避難面積": "1133.56"
    },
    "簷高": null,
    "建物高度": "47.3",
    "工程造價": "114147180",
    "竣工日期": "0910610",
    "開工日期": "0860226",
    "全建築地點": [
        "臺北市士林區基河路30號10樓之1",
        "臺北市士林區基河路30號10樓之2",
        "臺北市士林區基河路30號10樓之3",
        "臺北市士林區基河路30號10樓之5",
        "臺北市士林區基河路30號10樓之6",
        "臺北市士林區基河路30號10樓之7",
        "臺北市士林區基河路30號11樓之1",
        "臺北市士林區基河路30號11樓之2",
        "臺北市士林區基河路30號11樓之3",
        "臺北市士林區基河路30號11樓之5",
        "臺北市士林區基河路30號11樓之6",
        "臺北市士林區基河路30號11樓之7",
        "臺北市士林區基河路30號12樓之1",
        "臺北市士林區基河路30號12樓之2",
        "臺北市士林區基河路30號12樓之3",
        "臺北市士林區基河路30號12樓之5",
        "臺北市士林區基河路30號12樓之6",
        "臺北市士林區基河路30號13樓之1",
        "臺北市士林區基河路30號13樓之2",
        "臺北市士林區基河路30號13樓之3",
        "臺北市士林區基河路30號13樓之5",
        "臺北市士林區基河路30號2樓之1",
        "臺北市士林區基河路30號2樓之2",
        "臺北市士林區基河路30號2樓之3",
        "臺北市士林區基河路30號2樓之5",
        "臺北市士林區基河路30號2樓之6",
        "臺北市士林區基河路30號2樓之7",
        "臺北市士林區基河路30號3樓之1",
        "臺北市士林區基河路30號3樓之2",
        "臺北市士林區基河路30號3樓之3",
        "臺北市士林區基河路30號3樓之5",
        "臺北市士林區基河路30號3樓之6",
        "臺北市士林區基河路30號3樓之7",
        "臺北市士林區基河路30號4樓之1",
        "臺北市士林區基河路30號4樓之2",
        "臺北市士林區基河路30號4樓之3",
        "臺北市士林區基河路30號4樓之5",
        "臺北市士林區基河路30號4樓之6",
        "臺北市士林區基河路30號4樓之7",
        "臺北市士林區基河路30號5樓之1",
        "臺北市士林區基河路30號5樓之2",
        "臺北市士林區基河路30號5樓之3",
        "臺北市士林區基河路30號5樓之5",
        "臺北市士林區基河路30號5樓之6",
        "臺北市士林區基河路30號5樓之7",
        "臺北市士林區基河路30號6樓之1",
        "臺北市士林區基河路30號6樓之2",
        "臺北市士林區基河路30號6樓之3",
        "臺北市士林區基河路30號6樓之5",
        "臺北市士林區基河路30號6樓之6",
        "臺北市士林區基河路30號6樓之7",
        "臺北市士林區基河路30號7樓之1",
        "臺北市士林區基河路30號7樓之2",
        "臺北市士林區基河路30號7樓之3",
        "臺北市士林區基河路30號7樓之5",
        "臺北市士林區基河路30號7樓之6",
        "臺北市士林區基河路30號7樓之7",
        "臺北市士林區基河路30號8樓之1",
        "臺北市士林區基河路30號8樓之2",
        "臺北市士林區基河路30號8樓之3",
        "臺北市士林區基河路30號8樓之5",
        "臺北市士林區基河路30號8樓之6",
        "臺北市士林區基河路30號8樓之7",
        "臺北市士林區基河路30號9樓之1",
        "臺北市士林區基河路30號9樓之2",
        "臺北市士林區基河路30號9樓之3",
        "臺北市士林區基河路30號9樓之5",
        "臺北市士林區基河路30號9樓之6",
        "臺北市士林區基河路30號9樓之7",
        "臺北市士林區基河路30號",
        "臺北市士林區基河路32號",
        "臺北市士林區基河路34號",
        "臺北市士林區基河路36號",
        "臺北市士林區基河路38號",
        "臺北市士林區基河路40號10樓之1",
        "臺北市士林區基河路40號10樓之2",
        "臺北市士林區基河路40號10樓之3",
        "臺北市士林區基河路40號10樓之5",
        "臺北市士林區基河路40號10樓之6",
        "臺北市士林區基河路40號10樓之7",
        "臺北市士林區基河路40號11樓之1",
        "臺北市士林區基河路40號11樓之2",
        "臺北市士林區基河路40號11樓之3",
        "臺北市士林區基河路40號11樓之5",
        "臺北市士林區基河路40號11樓之6",
        "臺北市士林區基河路40號11樓之7",
        "臺北市士林區基河路40號12樓之1",
        "臺北市士林區基河路40號12樓之2",
        "臺北市士林區基河路40號12樓之3",
        "臺北市士林區基河路40號12樓之5",
        "臺北市士林區基河路40號12樓之6",
        "臺北市士林區基河路40號12樓之7",
        "臺北市士林區基河路40號13樓之1",
        "臺北市士林區基河路40號13樓之2",
        "臺北市士林區基河路40號13樓之3",
        "臺北市士林區基河路40號2樓之1",
        "臺北市士林區基河路40號2樓之2",
        "臺北市士林區基河路40號2樓之3",
        "臺北市士林區基河路40號2樓之5",
        "臺北市士林區基河路40號2樓之6",
        "臺北市士林區基河路40號3樓之1",
        "臺北市士林區基河路40號3樓之2",
        "臺北市士林區基河路40號3樓之3",
        "臺北市士林區基河路40號3樓之5",
        "臺北市士林區基河路40號3樓之6",
        "臺北市士林區基河路40號3樓之7",
        "臺北市士林區基河路40號4樓之1",
        "臺北市士林區基河路40號4樓之2",
        "臺北市士林區基河路40號4樓之3",
        "臺北市士林區基河路40號4樓之5",
        "臺北市士林區基河路40號4樓之6",
        "臺北市士林區基河路40號4樓之7",
        "臺北市士林區基河路40號5樓之1",
        "臺北市士林區基河路40號5樓之2",
        "臺北市士林區基河路40號5樓之3",
        "臺北市士林區基河路40號5樓之5",
        "臺北市士林區基河路40號5樓之6",
        "臺北市士林區基河路40號5樓之7",
        "臺北市士林區基河路40號6樓之1",
        "臺北市士林區基河路40號6樓之2",
        "臺北市士林區基河路40號6樓之3",
        "臺北市士林區基河路40號6樓之5",
        "臺北市士林區基河路40號6樓之6",
        "臺北市士林區基河路40號6樓之7",
        "臺北市士林區基河路40號7樓之1",
        "臺北市士林區基河路40號7樓之2",
        "臺北市士林區基河路40號7樓之3",
        "臺北市士林區基河路40號7樓之5",
        "臺北市士林區基河路40號7樓之6",
        "臺北市士林區基河路40號7樓之7",
        "臺北市士林區基河路40號8樓之1",
        "臺北市士林區基河路40號8樓之2",
        "臺北市士林區基河路40號8樓之3",
        "臺北市士林區基河路40號8樓之5",
        "臺北市士林區基河路40號8樓之6",
        "臺北市士林區基河路40號8樓之7",
        "臺北市士林區基河路40號9樓之1",
        "臺北市士林區基河路40號9樓之2",
        "臺北市士林區基河路40號9樓之3",
        "臺北市士林區基河路40號9樓之5",
        "臺北市士林區基河路40號9樓之6",
        "臺北市士林區基河路40號9樓之7",
        "臺北市士林區基河路40號",
        "臺北市士林區基河路42號",
        "臺北市士林區基河路46號2樓",
        "臺北市士林區基河路46號",
        "臺北市士林區基河路48號",
        "臺北市士林區劍潭路10號",
        "臺北市士林區劍潭路2-1號",
        "臺北市士林區劍潭路2號",
        "臺北市士林區劍潭路6號10樓之1",
        "臺北市士林區劍潭路6號10樓之2",
        "臺北市士林區劍潭路6號10樓之3",
        "臺北市士林區劍潭路6號10樓之5",
        "臺北市士林區劍潭路6號11樓之1",
        "臺北市士林區劍潭路6號11樓之2",
        "臺北市士林區劍潭路6號11樓之3",
        "臺北市士林區劍潭路6號12樓之1",
        "臺北市士林區劍潭路6號12樓之2",
        "臺北市士林區劍潭路6號12樓之3",
        "臺北市士林區劍潭路6號12樓之5",
        "臺北市士林區劍潭路6號13樓之1",
        "臺北市士林區劍潭路6號13樓之2",
        "臺北市士林區劍潭路6號2樓之1",
        "臺北市士林區劍潭路6號2樓之2",
        "臺北市士林區劍潭路6號2樓之3",
        "臺北市士林區劍潭路6號2樓之5",
        "臺北市士林區劍潭路6號3樓之1",
        "臺北市士林區劍潭路6號3樓之2",
        "臺北市士林區劍潭路6號3樓之3",
        "臺北市士林區劍潭路6號3樓之5",
        "臺北市士林區劍潭路6號4樓之1",
        "臺北市士林區劍潭路6號4樓之2",
        "臺北市士林區劍潭路6號4樓之3",
        "臺北市士林區劍潭路6號4樓之5",
        "臺北市士林區劍潭路6號5樓之1",
        "臺北市士林區劍潭路6號5樓之2",
        "臺北市士林區劍潭路6號5樓之3",
        "臺北市士林區劍潭路6號6樓之1",
        "臺北市士林區劍潭路6號6樓之2",
        "臺北市士林區劍潭路6號6樓之3",
        "臺北市士林區劍潭路6號6樓之5",
        "臺北市士林區劍潭路6號7樓之1",
        "臺北市士林區劍潭路6號7樓之2",
        "臺北市士林區劍潭路6號7樓之3",
        "臺北市士林區劍潭路6號7樓之5",
        "臺北市士林區劍潭路6號8樓之1",
        "臺北市士林區劍潭路6號8樓之2",
        "臺北市士林區劍潭路6號8樓之3",
        "臺北市士林區劍潭路6號8樓之5",
        "臺北市士林區劍潭路6號9樓之1",
        "臺北市士林區劍潭路6號9樓之2",
        "臺北市士林區劍潭路6號9樓之3",
        "臺北市士林區劍潭路6號9樓之5",
        "臺北市士林區劍潭路6號",
        "臺北市士林區劍潭路8號"
    ],
    "全地段地號": [
        "臺北市士林區光華段四小段0799-0000號"
    ],
    "建築概要": [
        "地下001樓,面積:75.4㎡,高度:3.5M,用途:社教設施(陳列館)",
        "地下001樓,面積:1058.16㎡,高度:3.5M,用途:停車場機房",
        "地下002樓,面積:1133.56㎡,高度:4.5M,用途:防空避難室兼停車空間",
        "地上001樓,面積:625.52㎡,高度:5.5M,用途:社教設施(陳列館)",
        "地上001樓,面積:149.04㎡,高度:5.5M,用途:門廳",
        "地上002樓,面積:621.74㎡,高度:3.2M,用途:集合住宅",
        "地上002樓,面積:65.65㎡,高度:3.2M,用途:一般事務所",
        "地上003樓,面積:647.66㎡,高度:3.2M,用途:集合住宅",
        "地上004樓,面積:647.66㎡,高度:3.2M,用途:集合住宅",
        "地上005樓,面積:647.66㎡,高度:3.2M,用途:集合住宅",
        "地上006樓,面積:647.66㎡,高度:3.2M,用途:集合住宅",
        "地上007樓,面積:647.66㎡,高度:3.2M,用途:集合住宅",
        "地上008樓,面積:647.66㎡,高度:3.2M,用途:集合住宅",
        "地上009樓,面積:647.66㎡,高度:3.2M,用途:集合住宅",
        "地上010樓,面積:647.66㎡,高度:3.2M,用途:集合住宅",
        "地上011樓,面積:647.66㎡,高度:3.2M,用途:集合住宅",
        "地上012樓,面積:642.7㎡,高度:3.2M,用途:集合住宅",
        "地上013樓,面積:410.23㎡,高度:3.08M,用途:集合住宅",
        "突出物001樓,面積:104.72㎡,高度:2.7M,用途:梯間、機房",
        "突出物002樓,面積:89.72㎡,高度:2.7M,用途:機房",
        "突出物003樓,面積:65.78㎡,高度:2.7M,用途:水箱"
    ],
    "雜項工作物": null,
    "全停車空間": [
        "設置類別:平面,車位分類:汽車,檢討類別:法定,室內,地下,輛數:57,面積:㎡",
        "設置類別:平面,車位分類:汽車,檢討類別:自設,室內,地下,輛數:5,面積:㎡",
        "設置類別:平面,車位分類:機車,檢討類別:法定,室內,地下,輛數:33,面積:㎡"
    ],
    "適用法令概要": null,
    "全注意事項": [
        "本府衛生下水道工程處審查核定之專用污水下水道計畫書及圖日後內容有變更時應報本府環保局備查",
        "取得建築物使用執照後，十天內將使照影本副知本府環保局，一個月內申請廢(污)水處理設施試車計畫(制式)，住戶進住率達50% 時應檢具污水處理設施功能測試合格報告書報本府環保局以備申領排放許可證，興建戶數500 戶以上者六個月內申請設置廢水處理專責人員",
        "備妥廢(污)水處理設施動力部份之專用獨立電表，並在放流口設置告示牌（請參閱下水道系統放流口告示牌範例）及放流口設置累計型流量計",
        "住戶遷入達百分之五十時檢具廢(污)水處理設施功能測試合格報告書向本府環保局申請廢(污)水排放許可審核，屆時未排放許可申領程序，將查處建設機構，本府環保局將依據申報資料進行水污染排放許可證之審查及核發作業",
        "污水下水道系統第一次變更管理單位時原建設機構應檢具1.污水處理設施移交清冊2.成立管理委員會時主管機關核備證明文件等負責向本府環保局辦理變更登記",
        "建築物樓層中任意加設夾層者均係屬違建，不因使用材質而視為室內裝修，除應無條件接受拆除，並負擔拆除費用，起造人向地政事務所申請建物所有權第一次登記時，地政事務所應依使用執照所載，於登記簿其他事項欄加註本建物不得加設夾層，違者無條件拆除並負擔拆除費用",
        "昇降設備需取得使用許可證後方可使用"
    ],
    "變更概要": {}
}