{
    "號碼": "069使字第1394號",
    "發照日期": "0691004",
    "原建照": "068建(雙園)(西園)字第0003號",
    "設計人": "何鳳？ (何鳳皋建築師事務所)",
    "監造人": "何鳳？ (何鳳皋建築師事務所)",
    "承造人": "劉耀薰(義峰營造股份有限公司)",
    "建造類別": "新建",
    "構造種類": "RC造、",
    "使用分區": "住宅區",
    "建物資訊": {
        "棟數": "3",
        "地上層數": "5",
        "地下層數": "1",
        "戶數": "30"
    },
    "建物面積": {
        "騎樓基地面積": "0",
        "其他基地面積": "692.13",
        "建築面積": "412.62",
        "法定空地面積": "0",
        "地上避難面積": "0",
        "地下避難面積": "248.69"
    },
    "簷高": "0",
    "建物高度": "14.2",
    "工程造價": "4489720",
    "竣工日期": "0690910",
    "開工日期": "0680410",
    "全建築地點": [
        "臺北市萬華區德昌街154巷38號2樓",
        "臺北市萬華區德昌街154巷38號3樓",
        "臺北市萬華區德昌街154巷38號4樓",
        "臺北市萬華區德昌街154巷38號5樓",
        "臺北市萬華區德昌街154巷38號",
        "臺北市萬華區德昌街154巷40號2樓",
        "臺北市萬華區德昌街154巷40號3樓",
        "臺北市萬華區德昌街154巷40號4樓",
        "臺北市萬華區德昌街154巷40號5樓",
        "臺北市萬華區德昌街154巷40號",
        "臺北市萬華區德昌街154巷42號2樓",
        "臺北市萬華區德昌街154巷42號3樓",
        "臺北市萬華區德昌街154巷42號4樓",
        "臺北市萬華區德昌街154巷42號5樓",
        "臺北市萬華區德昌街154巷42號",
        "臺北市萬華區德昌街154巷44號2樓",
        "臺北市萬華區德昌街154巷44號3樓",
        "臺北市萬華區德昌街154巷44號4樓",
        "臺北市萬華區德昌街154巷44號5樓",
        "臺北市萬華區德昌街154巷44號",
        "臺北市萬華區德昌街154巷46號2樓",
        "臺北市萬華區德昌街154巷46號3樓",
        "臺北市萬華區德昌街154巷46號4樓",
        "臺北市萬華區德昌街154巷46號5樓",
        "臺北市萬華區德昌街154巷46號",
        "臺北市萬華區德昌街154巷48號2樓",
        "臺北市萬華區德昌街154巷48號3樓",
        "臺北市萬華區德昌街154巷48號4樓",
        "臺北市萬華區德昌街154巷48號5樓",
        "臺北市萬華區德昌街154巷48號"
    ],
    "全地段地號": [
        "臺北市萬華區雙園段二小段0210-0024號",
        "臺北市萬華區雙園段二小段0210-0023號",
        "臺北市萬華區雙園段二小段0720-0000號",
        "臺北市萬華區雙園段二小段0721-0000號",
        "臺北市萬華區雙園段二小段0722-0000號",
        "臺北市萬華區雙園段二小段0723-0000號",
        "臺北市萬華區雙園段二小段0724-0000號"
    ],
    "建築概要": [
        "地下001樓,面積:248.69㎡,高度:2.7M,用途:防空避難室",
        "地上001樓,面積:412.62㎡,高度:2.9M,用途:停車場、集合住宅",
        "地上002樓,面積:412.62㎡,高度:2.8M,用途:集合住宅",
        "地上003樓,面積:412.62㎡,高度:2.8M,用途:集合住宅",
        "地上004樓,面積:385.47㎡,高度:2.8M,用途:集合住宅",
        "地上005樓,面積:330.84㎡,高度:2.78M,用途:集合住宅",
        "突出物001樓,面積:42㎡,高度:0M,用途:無"
    ],
    "雜項工作物": null,
    "全停車空間": [
        "設置類別:平面,車位分類:汽車,檢討類別:法定,室內,地下,輛數:2,面積:30㎡",
        "設置類別:平面,車位分類:汽車,檢討類別:法定,室外,地上,輛數:2,面積:30㎡"
    ],
    "適用法令概要": null,
    "全注意事項": [
        "1.第二層到第五層高度︰2.8M、2.78M",
        "2.建築高度︰14.2M、14.0M",
        "3.第一層高度︰2.9M、2.8M"
    ],
    "變更概要": {}
}