{
    "號碼": "083使字第0478號",
    "發照日期": "0831017",
    "原建照": "080建字第0245號",
    "設計人": "張坤德(台北市政府國民住宅處)",
    "監造人": "張坤德(台北市政府國民住宅處)",
    "承造人": "馬鄭隔(友明工程有限公司)",
    "建造類別": "新建",
    "構造種類": "RC造",
    "使用分區": "住3",
    "建物資訊": {
        "棟數": "1",
        "地上層數": "6",
        "地下層數": "1",
        "戶數": "24"
    },
    "建物面積": {
        "騎樓基地面積": "0",
        "其他基地面積": "1090.61",
        "建築面積": "418.76",
        "法定空地面積": "671.85",
        "地上避難面積": "0",
        "地下避難面積": "491.838"
    },
    "簷高": "0",
    "建物高度": "18.45",
    "工程造價": "18587526",
    "竣工日期": "0820924",
    "開工日期": "0801226",
    "全建築地點": [
        "臺北市北投區文化三路101號1樓",
        "臺北市北投區文化三路101號2樓",
        "臺北市北投區文化三路101號2樓",
        "臺北市北投區文化三路101號3樓",
        "臺北市北投區文化三路101號3樓",
        "臺北市北投區文化三路101號4樓",
        "臺北市北投區文化三路101號4樓",
        "臺北市北投區文化三路101號5樓",
        "臺北市北投區文化三路101號5樓",
        "臺北市北投區文化三路101號6樓",
        "臺北市北投區文化三路101號6樓",
        "臺北市北投區文化三路101號",
        "臺北市北投區文化三路95號1樓",
        "臺北市北投區文化三路95號2樓",
        "臺北市北投區文化三路95號2樓",
        "臺北市北投區文化三路95號3樓",
        "臺北市北投區文化三路95號3樓",
        "臺北市北投區文化三路95號4樓",
        "臺北市北投區文化三路95號4樓",
        "臺北市北投區文化三路95號5樓",
        "臺北市北投區文化三路95號5樓",
        "臺北市北投區文化三路95號6樓",
        "臺北市北投區文化三路95號6樓",
        "臺北市北投區文化三路95號",
        "臺北市北投區文化三路97號1樓",
        "臺北市北投區文化三路97號2樓",
        "臺北市北投區文化三路97號2樓",
        "臺北市北投區文化三路97號3樓",
        "臺北市北投區文化三路97號3樓",
        "臺北市北投區文化三路97號4樓",
        "臺北市北投區文化三路97號4樓",
        "臺北市北投區文化三路97號5樓",
        "臺北市北投區文化三路97號5樓",
        "臺北市北投區文化三路97號6樓",
        "臺北市北投區文化三路97號6樓",
        "臺北市北投區文化三路97號",
        "臺北市北投區文化三路99號1樓",
        "臺北市北投區文化三路99號2樓",
        "臺北市北投區文化三路99號2樓",
        "臺北市北投區文化三路99號3樓",
        "臺北市北投區文化三路99號3樓",
        "臺北市北投區文化三路99號4樓",
        "臺北市北投區文化三路99號4樓",
        "臺北市北投區文化三路99號5樓",
        "臺北市北投區文化三路99號5樓",
        "臺北市北投區文化三路99號6樓",
        "臺北市北投區文化三路99號6樓",
        "臺北市北投區文化三路99號"
    ],
    "全地段地號": [
        "臺北市北投區秀山段二小段0659-0001號"
    ],
    "建築概要": [
        "地下001樓,面積:491.84㎡,高度:3.2M,用途:防空避難室兼停車場",
        "地上001樓,面積:418.76㎡,高度:3M,用途:日常用品零售業",
        "地上002樓,面積:404.56㎡,高度:2.9M,用途:集合住宅",
        "地上003樓,面積:404.56㎡,高度:2.9M,用途:集合住宅",
        "地上004樓,面積:404.56㎡,高度:2.9M,用途:集合住宅",
        "地上005樓,面積:404.56㎡,高度:2.9M,用途:集合住宅",
        "地上006樓,面積:404.56㎡,高度:2.9M,用途:集合住宅",
        "突出物001樓,面積:21.6㎡,高度:2.95M,用途:樓梯間",
        "突出物002樓,面積:42.99㎡,高度:2.95M,用途:機械室、水箱"
    ],
    "雜項工作物": null,
    "全停車空間": [
        "設置類別:平面,車位分類:汽車,檢討類別:法定,室內,地下,輛數:4,面積:60㎡"
    ],
    "適用法令概要": null,
    "全注意事項": [
        "1.法定空地面積671.85m2",
        "2.電梯昇降机須經檢查合格領得使用許可證後方能使用",
        "3.已領有衛生下水道工程處82年12月7日（82）戶用證字097號用戶衛生排水設備使用許可證"
    ],
    "變更概要": {}
}