{
    "號碼": "058使字第1889號",
    "發照日期": "0581222",
    "原建照": "055建(肆)(安)字第0088號",
    "設計人": "廖鵬程(天工建築師事務所)",
    "監造人": "廖鵬程(天工建築師事務所)",
    "承造人": "楊文藝(明東營造廠)",
    "建造類別": "新建",
    "構造種類": "加強磚造、",
    "使用分區": "住宅區",
    "建物資訊": {
        "棟數": "8",
        "地上層數": "3",
        "地下層數": "0",
        "戶數": "24"
    },
    "建物面積": {
        "騎樓基地面積": "141.96",
        "其他基地面積": "899.34",
        "建築面積": "0",
        "法定空地面積": "0",
        "地上避難面積": "0",
        "地下避難面積": "0"
    },
    "簷高": "0",
    "建物高度": "0",
    "工程造價": "1280000",
    "竣工日期": "0580725",
    "開工日期": "0551215",
    "全建築地點": [
        "臺北市大安區復興南路二段295-1號",
        "臺北市大安區復興南路二段295-2號",
        "臺北市大安區復興南路二段295號",
        "臺北市大安區復興南路二段297-1號",
        "臺北市大安區復興南路二段297-2號",
        "臺北市大安區復興南路二段297號",
        "臺北市大安區復興南路二段299-1號",
        "臺北市大安區復興南路二段299-2號",
        "臺北市大安區復興南路二段299號",
        "臺北市大安區復興南路二段301-1號",
        "臺北市大安區復興南路二段301-2號",
        "臺北市大安區復興南路二段301號",
        "臺北市大安區復興南路二段303-1號",
        "臺北市大安區復興南路二段303-2號",
        "臺北市大安區復興南路二段303號",
        "臺北市大安區復興南路二段305-1號",
        "臺北市大安區復興南路二段305-2號",
        "臺北市大安區復興南路二段305號",
        "臺北市大安區復興南路二段307-1號",
        "臺北市大安區復興南路二段307-2號",
        "臺北市大安區復興南路二段307號",
        "臺北市大安區復興南路二段309-1號",
        "臺北市大安區復興南路二段309-2號",
        "臺北市大安區復興南路二段309號"
    ],
    "全地段地號": [
        "臺北市大安區龍安坡段0669-0000號",
        "臺北市大安區下內埔段0127-0001號"
    ],
    "建築概要": null,
    "雜項工作物": null,
    "全停車空間": null,
    "適用法令概要": null,
    "全注意事項": null,
    "變更概要": {}
}