{
    "號碼": "085使字第0190號",
    "發照日期": "0850523",
    "原建照": "084建字第0253號",
    "設計人": "江正宗(江正宗)",
    "監造人": "江正宗(江正宗)",
    "承造人": "李文(宏賓營造股份有限公司)",
    "建造類別": "新建",
    "構造種類": "RC造",
    "使用分區": "住3",
    "建物資訊": {
        "棟數": "2",
        "地上層數": "5",
        "地下層數": "1",
        "戶數": "40"
    },
    "建物面積": {
        "騎樓基地面積": "0",
        "其他基地面積": "1200.5",
        "建築面積": "540.21",
        "法定空地面積": "600.25",
        "地上避難面積": "0",
        "地下避難面積": "954.99"
    },
    "簷高": "16.58",
    "建物高度": "16.7",
    "工程造價": "22414476",
    "竣工日期": null,
    "開工日期": "0840724",
    "全建築地點": [
        "臺北市文山區光輝路134巷10弄2號2樓",
        "臺北市文山區光輝路134巷10弄2號3樓",
        "臺北市文山區光輝路134巷10弄2號4樓",
        "臺北市文山區光輝路134巷10弄2號5樓",
        "臺北市文山區光輝路134巷10弄2號",
        "臺北市文山區光輝路134巷10弄4號2樓",
        "臺北市文山區光輝路134巷10弄4號3樓",
        "臺北市文山區光輝路134巷10弄4號4樓",
        "臺北市文山區光輝路134巷10弄4號5樓",
        "臺北市文山區光輝路134巷10弄4號",
        "臺北市文山區光輝路134巷10弄6號2樓",
        "臺北市文山區光輝路134巷10弄6號3樓",
        "臺北市文山區光輝路134巷10弄6號4樓",
        "臺北市文山區光輝路134巷10弄6號5樓",
        "臺北市文山區光輝路134巷10弄6號",
        "臺北市文山區光輝路134巷10弄8號2樓",
        "臺北市文山區光輝路134巷10弄8號3樓",
        "臺北市文山區光輝路134巷10弄8號4樓",
        "臺北市文山區光輝路134巷10弄8號5樓",
        "臺北市文山區光輝路134巷10弄8號",
        "臺北市文山區光輝路134巷2號2樓",
        "臺北市文山區光輝路134巷2號3樓",
        "臺北市文山區光輝路134巷2號4樓",
        "臺北市文山區光輝路134巷2號5樓",
        "臺北市文山區光輝路134巷2號",
        "臺北市文山區光輝路134巷4號2樓",
        "臺北市文山區光輝路134巷4號3樓",
        "臺北市文山區光輝路134巷4號4樓",
        "臺北市文山區光輝路134巷4號5樓",
        "臺北市文山區光輝路134巷4號",
        "臺北市文山區光輝路134巷6號2樓",
        "臺北市文山區光輝路134巷6號3樓",
        "臺北市文山區光輝路134巷6號4樓",
        "臺北市文山區光輝路134巷6號5樓",
        "臺北市文山區光輝路134巷6號",
        "臺北市文山區光輝路134巷8號2樓",
        "臺北市文山區光輝路134巷8號3樓",
        "臺北市文山區光輝路134巷8號4樓",
        "臺北市文山區光輝路134巷8號5樓",
        "臺北市文山區光輝路134巷8號"
    ],
    "全地段地號": [
        "臺北市文山區實踐段一小段0305-0006號"
    ],
    "建築概要": [
        "地下001樓,面積:1097.02㎡,高度:5.15M,用途:防空避難室兼停車空間",
        "地上001樓,面積:540.21㎡,高度:3.1M,用途:集合住宅",
        "地上002樓,面積:540.21㎡,高度:3.1M,用途:集合住宅",
        "地上003樓,面積:540.21㎡,高度:3.1M,用途:集合住宅",
        "地上004樓,面積:540.21㎡,高度:3.1M,用途:集合住宅",
        "地上005樓,面積:540.21㎡,高度:2.98M,用途:集合住宅",
        "突出物001樓,面積:37.41㎡,高度:2.8M,用途:樓梯間",
        "突出物002樓,面積:37.95㎡,高度:2.5M,用途:水箱、水塔"
    ],
    "雜項工作物": [
        "圍牆長度223.95m高度1.80m"
    ],
    "全停車空間": [
        "設置類別:平面,車位分類:,檢討類別:,室內,,輛數:15,面積:212.65㎡"
    ],
    "適用法令概要": null,
    "全注意事項": null,
    "變更概要": {}
}