{
    "號碼": "080使字第0298號",
    "發照日期": "0800607",
    "原建照": "078建(士林)字第0524號",
    "設計人": "張錦章(張錦章)",
    "監造人": "張錦章(張錦章建築師事務所)",
    "承造人": "許水波(正倫營造股份有限公司)",
    "建造類別": "新建",
    "構造種類": "RC造",
    "使用分區": "保護區",
    "建物資訊": {
        "棟數": "1",
        "地上層數": "2",
        "地下層數": "0",
        "戶數": "1"
    },
    "建物面積": {
        "騎樓基地面積": "0",
        "其他基地面積": "652.83",
        "建築面積": "117.9",
        "法定空地面積": "534.9",
        "地上避難面積": "0",
        "地下避難面積": "0"
    },
    "簷高": "0",
    "建物高度": "7",
    "工程造價": "723610",
    "竣工日期": "0800207",
    "開工日期": "0790306",
    "全建築地點": [
        "臺北市士林區士東路353巷6-1號"
    ],
    "全地段地號": [
        "臺北市士林區芝蘭段二小段0415-0000號"
    ],
    "建築概要": [
        "1棟地上001樓,面積:117.9㎡,高度:3.1M,用途:農舍；",
        "1棟地上002樓,面積:99.9㎡,高度:3.1M,用途:農舍；",
        "1棟突出物001樓,面積:14.72㎡,高度:2.5M,用途:水箱；"
    ],
    "雜項工作物": null,
    "全停車空間": null,
    "適用法令概要": null,
    "全注意事項": [
        "法定空地面積534.90平方公尺"
    ],
    "變更概要": {}
}